Workbook

Sheet Notas e Inst. de la Versión
A5: PCI DSS v4.0 - Herramienta de Enfoque Prioritario r1
A6: Notas e Instrucciones de la Versión
A7: Febrero de 2023
A9: Contenidos: 4 hojas de cálculo (ver fichas al final de esta página)
A10: · Notas e Instrucciones de la Versión (esta tabla)
A11: · Resumen de los Cambios
A12: · Hitos del Enfoque Prioritario
A13: · Resumen del Enfoque Prioritario
A15: Propósito: Herramienta para el seguimiento del progreso hacia la conformidad de PCI DSS versión 4.0 mediante el uso del Enfoque Prioritario. También se proporciona una herramienta de clasificación para analizar el progreso por requisito PCI DSS, categoría de hito o estado de hito.
A16: Paso 1: Indique "Sí", "No" o "N/A" en la columna C de la pestaña de la hoja de cálculo "Hitos del Enfoque Prioritario". Este paso completará automáticamente los campos de "porcentaje completo" en la pestaña de la hoja de cálculo "Resumen del Enfoque Prioritario".
A17: Sí | B17: Todos los elementos del requisito se han cumplido.
A18: No | B18: Algunos o todos los elementos del requisito no se han cumplido, o están en proceso de ser implementados, o requieren más pruebas antes de que el comerciante pueda confirmar que han sido implementados.
A19: N/A | B19: El requisito no aplica para el entorno de la entidad. Por ejemplo, un comerciante utilizaría N/A para aquellos requisitos que sólo se aplican si la entidad evaluada es un proveedor de servicios.
A20: Requisitos con Fecha Futura: No se requiere que estos nuevos requisitos se incluyan en una evaluación PCI DSS hasta que haya pasado la fecha futura. Antes de esa fecha futura, cualquier requisito nuevo con una fecha de implementación extendida que la entidad no haya implementado puede marcarse como N/A.
A21: Paso 2: Análisis de resultados. Utilice las funciones de "filtro" en los encabezados de las columnas de la pestaña de la hoja de cálculo "Hitos del Enfoque Prioritario" para seleccionar cualquiera de los seis hitos.
A22: Paso 3: Complete la Información de la Organización en la pestaña "Resumen del Enfoque Prioritario". Puede compartir este documento con su adquirente o con un evaluador de seguridad cualificado para que le proporcione una evaluación del progreso que su organización ha completado para lograr la conformidad de PCI DSS. También puede introducir manualmente una fecha estimada de finalización para cada fase de los hitos. Verifique con su adquirente las instrucciones específicas de presentación.
A23: Paso 4: Cuando consiga alcanzar el 100% de todos los requisitos enumerados en la categoría de hitos, hable con su adquirente o con las marcas de pago sobre los siguientes pasos. Las preguntas sobre el uso del Enfoque Prioritario y cómo el uso del Enfoque Prioritario puede afectar a las obligaciones de conformidad de una organización deben dirigirse a su adquirente o a las marcas de pago a las que su organización informa de la conformidad.
A24: Declaraciones: Este documento no modifica ni reduce a PCI DSS ni a ninguno de sus requisitos y puede ser modificado sin previo aviso. PCI SSC no se hace responsable de los errores o daños de cualquier tipo resultantes del uso de la información aquí contenida. PCI SSC no ofrece ninguna garantía o representación en relación con la información proporcionada en este documento y no asume ninguna responsabilidad en relación con el uso o el mal uso de dicha información.

Sheet Resumen de los Cambios
A7: PCI DSS v4.0 - Herramienta de Enfoque Prioritario r1
A8: Resumen de los Cambios
A9: Febrero de 2023
A11: Cambios en los Documentos
A13: Fecha | C13: Revisión | F13: Descripción
A14: Agosto de 2022 | C14: Herramienta de Enfoque Prioritario PCI DSS v4.0 | F14: Versión inicial para PCI DSS v4.0
A15: Febrero de 2023 | C15: PCI DSS v4.0 - Herramienta de Enfoque Prioritario r1 | F15: Las actualizaciones incluyen: - Inclusión de una pestaña de Resumen de Cambios - Explicación de las opciones de respuesta "Sí", "No" y "N/A", y cómo responder a los nuevos requisitos de PCI DSS v4.0 que no se requieren hasta el 31 de marzo de 2025 - Alineación de título y versión PCI DSS - Corrección de fórmula de hoja de cálculo - Actualizaciones a celdas editables

Sheet Resumen del Enfoque Prioritario
B5: Resumen del Enfoque Prioritario y Reconocimiento
B7: Parte 1: Información de Contacto
B8: Nombre de la Compañía | E8: Dirección Postal de la Compañía
B9: DBA (Actuando Comercialmente Como) | E9: Página Web Principal de la Compañía
B10: Nombre del Contacto de la Compañía
B11: Título del Contacto de la Compañía
B12: Número de Teléfono de Contacto
B13: Dirección de Correo Electrónico del Contacto
B15: Parte 2a: Canales de Pago Comerciales (Seleccione todos los que correspondan) | E15: Parte 2b: Empresa Proveedora de Servicios (Seleccione todo lo que corresponda)
B16: Pedido por correo/teléfono (MOTO) | E16: Proveedor de Alojamiento: | F16: Servicios Administrados: | G16: Procesamiento de Pagos:
B17: Comercio Electrónico | E17: Aplicaciones / software | F17: Servicios de seguridad del sistemas | G17: POI / tarjeta presencial
B18: Tarjeta presencial | E18: Hardware | F18: Apoyo TI | G18: Internet - comercio electrónico
B19: Otros procesamientos (especifique): | E19: Infraestructura / Red | F19: Seguridad Física | G19: MOTO / Centro de Llamadas
E20: Espacio físico (co-ubicación) | F20: Sistema de Gestión de Terminal | G20: ATM
B21: Parte 3: Relaciones | E21: Almacenamiento | F21: Otros servicios (especifique): | G21: Otros procesamientos (especifique):
B22: ¿Tiene su organización relación con uno o más agentes de terceros? | E22: Servicios de alojamiento Web
B23: (Por ejemplo: pasarelas, empresas de alojamiento web, agentes de reservas de aerolíneas, | E23: Servicios de seguridad
B24: agentes de programas de fidelización, etc) | E24: Proveedor de Hospedaje Seguro 3-D
E25: Proveedor de Servicios Multi-Usuario
E26: Otro tipo de Hospedaje (especifique):
B27: ¿Tiene su organización una relación con mas de un adquiriente?
E28: Gestión de Cuentas | F28: Fraude y Devoluciones | G28: Pasarela de Pagos/Conmutador
E29: Servicios Administrativos | F29: Procesamiento de Emisor | G29: Servicios Prepago
E30: Gestión de Facturación | F30: Programas de Lealtad | G30: Gestión de Registros
E31: Compensación y Liquidación | F31: Servicios Comerciales | G31: Pagos de Impuestos/Gobierno
E32: Proveedor de Red
E33: Otros (especifique):
B34: Parte 4: Procesamiento de Transacciones
B35: Aplicaciones de Pago en uso | E35: Enumere las instalaciones y ubicaciones incluidas en la Evaluación PCI DSS:
B36: Versión de la Aplicación de Pago
B49: Resumen del Enfoque Prioritario y Reconocimiento
B51: Hito | C51: Objetivos | F51: Porcentaje Completo | G51: Fecha Estimada de Finalización por Hito
B52: 1 | C52: No almacenar datos confidenciales de autenticación y limitar la retención de datos de tarjetahabientes. Este hito se dirige a un área clave de riesgo para las entidades que se han visto comprometidas. Recuerde: si no se almacenan datos confidenciales de autenticación y otros datos de tarjetahabientes los efectos de un compromiso se reducirán en gran medida. Si no lo necesita, no lo almacene. | F52: =IFERROR((Calcs!A341)/(COUNTIF('Hitos del Enfoque Prioritario'!B5:B341,"1")-(Calcs!H341)),1) -> 0 | G52: =IF(Calcs!AB341>0,"Falta la Fecha de Finalización",(IF(MAX(Calcs!P4:P341)=0,"",MAX(Calcs!P4:P341))))
B53: 2 | C53: Proteja los sistemas y las redes y esté preparado para responder a una infracción del sistema. Este hito tiene como objetivo los controles de los puntos de acceso a la mayoría de los compromisos y a los procesos de respuesta. | F53: =IFERROR((Calcs!B341)/(COUNTIF('Hitos del Enfoque Prioritario'!B5:B341,"2")-(Calcs!I341)),1) -> 0 | G53: =IF(Calcs!AC341>0,"Falta la Fecha de Finalización",(IF(MAX(Calcs!Q4:Q341)=0,"",MAX(Calcs!Q4:Q341))))
B54: 3 | C54: Aplicaciones de pago seguras. Este hito se dirige a los controles de las aplicaciones, los procesos de aplicación y los servidores de aplicaciones. Los puntos débiles en estas áreas son presa fácil para comprometer los sistemas y obtener acceso a los datos de tarjetahabientes. | F54: =IFERROR((Calcs!C341)/(COUNTIF('Hitos del Enfoque Prioritario'!B5:B341,"3")-(Calcs!J341)),1) -> 0 | G54: =IF(Calcs!AD341>0,"Falta la Fecha de Finalización",(IF(MAX(Calcs!R4:R341)=0,"",MAX(Calcs!R4:R341))))
B55: 4 | C55: Supervise y controle el acceso a sus sistemas. Los controles de este hito le permiten detectar el quién, el qué, el cuándo y el cómo en relación con el acceso a su red y al entorno de datos de tarjetahabientes. | F55: =IFERROR((Calcs!D341)/(COUNTIF('Hitos del Enfoque Prioritario'!B5:B341,"4")-(Calcs!K341)),1) -> 0 | G55: =IF(Calcs!AE341>0,"Falta la Fecha de Finalización",(IF(MAX(Calcs!S4:S341)=0,"",MAX(Calcs!S4:S341))))
B56: 5 | C56: Proteger los datos de tarjetahabientes almacenados. Para aquellas organizaciones que han analizado sus procesos de negocio y han determinado que deben almacenar Números de Cuenta Primarios, este hito se centra en los mecanismos de protección clave para los datos almacenados. | F56: =IFERROR((Calcs!E341)/(COUNTIF('Hitos del Enfoque Prioritario'!B5:B341,"5")-(Calcs!L341)),1) -> 0 | G56: =IF(Calcs!AF341>0,"Falta la Fecha de Finalización",(IF(MAX(Calcs!T4:T341)=0,"",MAX(Calcs!T4:T341))))
B57: 6 | C57: Finalice los esfuerzos de conformidad restantes y asegúrese de que todos los controles están implementados. Este hito completa los requisitos PCI DSS y finaliza todas las políticas, procedimientos y procesos relacionados restantes necesarios para proteger el entorno de datos de tarjetahabientes. | F57: =IFERROR((Calcs!F341)/(COUNTIF('Hitos del Enfoque Prioritario'!B5:B341,"6")-(Calcs!M341)),1) -> 0 | G57: =IF(Calcs!AG341>0,"Falta la Fecha de Finalización",(IF(MAX(Calcs!U4:U341)=0,"",MAX(Calcs!U4:U341))))
B58: General | F58: =Calcs!G341/(COUNT('Hitos del Enfoque Prioritario'!B5:B341)-Calcs!N341) -> 0 | G58: =IF(MAX(F52:F57)=0,"",MAX(G52:G57))
B60: A la organización que presente este formulario se le puede exigir que complete un Plan de Acción, que se encuentra en cada Certificado de Conformidad en la Parte 4: Plan de Acción para los Requisitos que se encuentran en situación de No Conformidad. Consulte con su entidad adquirente o con la(s) marca(s) de pago, ya que no todas las marcas de pago requieren completar un Plan de Acción.
B61: La Herramienta de Enfoque Prioritario se proporciona para asistir a las organizaciones que buscan lograr la conformidad, pero no modifica ni pretende en modo alguno limitar a PCI DSS ni ninguno de sus requisitos.
B62: Parte 5: Fecha Límite para Lograr la Plena Conformidad PCI DSS | E62: Fecha (AAA-MM-DD)
B63: Parte 6: Reconocimientos de la Organización (y QSA si corresponde)
B64: Nombre del Funcionario Ejecutivo
B65: Firma del Funcionario Ejecutivo | E65: Fecha (AAA-MM-DD)
B66: Nombre del QSA Principal (si corresponde)
B67: Firma del QSA | E67: Fecha (AAA-MM-DD)

Sheet Hitos del Enfoque Prioritario
A1: Requisitos PCI DSS v4.0 | B1: Hito | C1: Estado Por favor, introduzca "sí" si está totalmente en conformidad con el requisito | D1: Si el estado es "N/A", explique por qué el requisito No es Aplicable | E1: Si el estado es "No", complete lo siguiente
E2: Etapa de Implementación | F2: Fecha Estimada de Finalización por Hito | G2: Comentarios
A3: Requisito 1: Instalar y Mantener los Controles de Seguridad de la Red
A4: 1.1 Se definen y comprenden los procesos y mecanismos para instalar y mantener los controles de seguridad de la red.
A5: 1.1.1 Todas las políticas de seguridad y procedimientos operativos que se identifican en el Requisito 1 son: • Documentados. • Actualizados. • En uso. • Conocidos por todas las partes involucradas. | B5: 6
A6: 1.1.2 Los roles y responsabilidades para realizar las actividades del Requisito 1 están documentados, asignados y comprendidos. | B6: 6
A7: 1.2 Se configuran y mantienen los controles de seguridad de la red (NSC).
A8: 1.2.1 Los estándares de configuración para el conjunto de reglas de los NSC son: • Definidos. • Implementados. • Mantenido. | B8: 2
A9: 1.2.2 Todos los cambios en las conexiones de red y en las configuraciones de los NSC se aprueban y gestionan de acuerdo con el proceso de control de cambios definido en el Requisito 6.5.1. Notas de Aplicabilidad Los cambios en las conexiones de red incluyen la adición, eliminación o modificación de una conexión. Los cambios en las configuraciones del NSC incluyen aquellos relacionados con el propio componente, así como los que afectan la forma en que realiza su función de seguridad. | B9: 6
A10: 1.2.3 Se mantiene un diagrama de red precisos que muestra todas las conexiones entre el CDE y otras redes, incluyendo las redes inalámbricas. Notas de Aplicabilidad Se puede utilizar un(os) diagrama(s) de red vigente(s) u otra solución técnica o topológica que identifique las conexiones y dispositivos en la red para cumplir con este requisito. | B10: 1
A11: 1.2.4 Se mantienen diagramas de flujo de datos precisos que cumplen con lo siguiente: • Muestran todos los flujos de datos de tarjetahabientes a través de sistemas y redes. • Se actualizan según sea necesario ante cambios en el entorno. Notas de Aplicabilidad Se puede utilizar un diagrama de flujo de datos u otra solución técnica o topológica que identifique los flujos de datos de tarjetahabientes a través de sistemas y redes para cumplir con este requisito. | B11: 1
A12: 1.2.5 Todos los servicios, protocolos y puertos permitidos están identificados, aprobados y tienen una necesidad de negocio definida. | B12: 2
A13: 1.2.6 Las configuraciones de seguridad son definidas e implementadas para todos los servicios, protocolos y puertos que están en uso y que son considerados inseguros, de tal manera que el riesgo es mitigado. | B13: 2
A14: 1.2.7 Las configuraciones de los NSC se revisan al menos una vez cada seis meses para confirmar que son relevantes y eficientes. | B14: 6
A15: 1.2.8 Los archivos de configuración de los NSC están: • Asegurados contra el acceso no autorizado. • Se mantienen consistentes con las configuraciones de red activas. Notas de Aplicabilidad Cualquier archivo o ajuste utilizado para configurar o sincronizar los NSC se considera un “archivo de configuración.” Esto incluye archivos, controles automatizados y basados en el sistema, scripts, configuraciones, infraestructura como código u otros parámetros de los que se hace una copia de seguridad, se archivan o se almacenan de forma remota. | B15: 2
A16: 1.3 El acceso a la red hacia y desde el entorno de datos de tarjetahabientes está restringido.
A17: 1.3.1 El tráfico de entrada al CDE está restringido de la siguiente manera: • Sólo el tráfico que sea necesario, • Todo el resto del tráfico está específicamente denegado. | B17: 2
A18: 1.3.2 El tráfico saliente del CDE se restringe de la siguiente manera: • Sólo al tráfico necesario. • Todo el resto del tráfico está específicamente denegado. | B18: 2
A19: 1.3.3 Los NSC se implementan entre todas las redes inalámbricas y el CDE; esto es independientemente de que la red inalámbrica sea parte CDE o no, de manera que: • Todo el tráfico inalámbrico de las redes inalámbricas hacia el CDE es denegado de forma explícita. • Sólo se permite el tráfico inalámbrico al CDE que tenga un propósito de negocio autorizado. | B19: 2
A20: 1.4 Se controlan las conexiones de red entre las redes fiables y las que no lo son.
A21: 1.4.1 Los NSC se implementan entre redes confiables y no confiables. | B21: 2
A22: 1.4.2 El tráfico entrante de redes que no son confiables a redes confiables está restringido a: • Las comunicaciones con componentes del sistema autorizados para proveer servicios de acceso público, protocolos y puertos. • Respuestas las comunicaciones previamente iniciadas por componentes del sistema en una red confiable, esto para protocolos con dicho comportamiento. • Todo el tráfico restante está denegado. Notas de Aplicabilidad La intención de este requisito es abordar las sesiones de comunicación entre redes fiables y no fiables, en lugar de las especificaciones de los protocolos. Este requisito no limita el uso de UDP u otros protocolos de red no orientados a conexión si el comportamiento estándar del estado de la conexión del protocolo es mantenido y bajo el control del NSC. | B22: 2
A23: 1.4.3 Se implementan medidas Antispoofing para detectar y bloquear la entrada a la red confiable de direcciones IP origen falsas o suplantadas. | B23: 2
A24: 1.4.4 Los componentes del sistema que almacenan datos de tarjetahabientes no son accesibles directamente desde redes no confiables. Notas de Aplicabilidad Este requisito no se aplica al almacenamiento de datos de tarjetahabientes en memoria volátil, pero sí se aplica cuando la memoria se trata como almacenamiento persistente (por ejemplo, disco RAM). Los datos de tarjetahabientes sólo pueden almacenarse en la memoria volátil durante el tiempo necesario para apoyar el proceso de negocio asociado (por ejemplo, hasta la finalización transacción relacionada con tarjeta de pago). | B24: 2
A25: 1.4.5 La divulgación de las direcciones IP internas y la información de enrutamiento se limita sólo a las partes autorizadas. | B25: 2
A26: 1.5 Se mitigan los riesgos para el CDE desde dispositivos informáticos que pueden conectarse tanto a redes no confiables como al CDE.
A27: 1.5.1 Los controles de seguridad se implementan en cualquier dispositivo informático, incluyendo los dispositivos propiedad de la empresa y de los empleados, que se conectan tanto a redes no confiables (incluida Internet) como al CDE manera siguiente. • Se definen los parámetros de configuración específicos para impedir que se introduzcan amenazas en la red de la entidad. • Los controles de seguridad se están ejecutando activamente. • Los usuarios de los dispositivos informáticos no pueden alterar los controles de seguridad a menos que estén específicamente documentados y autorizados por el nivel gerencial, caso por caso, durante un período limitado. Notas de Aplicabilidad Estos controles de seguridad pueden desactivarse temporalmente solo si existe una necesidad técnica legítima, según lo autorizado por el nivel gerencial caso por caso. Se requiere de una autorización formal para desactivar estos controles de seguridad para y bajo un propósito específico. También puede ser necesario implementar medidas de seguridad adicionales durante el período durante el cual los controles de seguridad estén desactivados. Este requisito aplica a los dispositivos informáticos que sean propiedad tanto de la compañía como de los empleados. Los sistemas que no pueden ser administrados por políticas corporativas introducen debilidades y brindan oportunidades para que personas malintencionadas pueden explotarlas y/o aprovecharlas. | B27: 2
A28: Requisito 2: Aplicar Configuraciones Seguras a Todos los Componentes del Sistema
A29: 2.1 Se definen y comprenden los procesos y mecanismos para aplicar configuraciones seguras a todos los componentes del sistema.
A30: 2.1.1Todas las políticas de seguridad y procedimientos operativos que se identifican en el Requisito 2 están: • Documentados. • Actualizados. • En uso. • Conocidos por todas las partes involucradas. | B30: 6
A31: 2.1.2 Los roles y responsabilidades para realizar las actividades del Requisito 2 están documentados, asignados y comprendidos. Nuevo requisito - efectivo inmediatamente | B31: 6
A32: 2.2 Los componentes del sistema se configuran y administran de forma segura.
A33: 2.2.1 Las estándares de configuración se desarrollan, implementan y mantienen para: • Cubrir todos los componentes del sistema. • Cubrir todas las vulnerabilidades de seguridad conocidas. • Brindar coherencia con los estándares de hardening del sistema aceptados por el sector o con las recomendaciones de hardening del proveedor. • Ser actualizadas a medida que se identifican nuevos problemas de vulnerabilidad, como se define en el Requisito 6.3.1. • Ser aplicadas cuando los nuevos sistemas sean configurados y verificadas como establecidas antes o inmediatamente después de que un componente del sistema se conecte a un entorno de producción. | B33: 2
A34: 2.2.2 Las cuentas predeterminadas del proveedor se gestionan de la siguiente manera: • Si se utilizan las cuentas predeterminadas del proveedor, la contraseña predeterminada se cambia según el Requisito 8.3.6. • Si no se van a utilizar las cuentas predeterminadas del proveedor, la cuenta se elimina o se desactiva. Notas de Aplicabilidad Esto se aplica a TODAS las cuentas y contraseñas predeterminadas del proveedor, incluidas, entre otras, las utilizadas por los sistemas operativos, el software que proporciona servicios de seguridad, las cuentas de aplicaciones y sistemas, los terminales de punto de venta (POS), las aplicaciones de pago y los valores predeterminadas del Simple Network Management Protocol (SNMP). Este requisito también se aplica cuando un componente del sistema no está instalado en el entorno de una entidad, por ejemplo, el software y las aplicaciones que forman parte del CDE y a las que se ingresa a través de un servicio de suscripción en la nube. | B34: 2
A35: 2.2.3 Las funciones principales que requieren distintos niveles de seguridad se manejan como sigue: • Solo existe una función principal en un componente del sistema, O • Las funciones principales con distintos niveles de seguridad que existen en el mismo componente del sistema están aisladas entre sí, O • Las funciones primarias con distintos niveles de seguridad en el mismo componente del sistema están todas aseguradas al nivel requerido por la función que requiera un nivel mayor de seguridad. | B35: 2
A36: 2.2.4 Sólo se habilitan los servicios, protocolos, «demonios» y funciones necesarias, y se eliminan o deshabilitan todas las funciones innecesarias. | B36: 2
A37: 2.2.5 Si existen servicios, protocolos o «demonios» inseguros: • La justificación de negocio está documentada. • Se documentan e implementan características de seguridad adicionales que reducen el riesgo de utilizar servicios, protocolos o «demonios» inseguros. | B37: 2
A38: 2.2.6 Los parámetros de seguridad del sistema están configurados para impedir su uso indebido. | B38: 2
A39: 2.2.7 Todo el acceso administrativo sin consola está cifrado utilizando criptografía robusta. Notas de Aplicabilidad Esto incluye el acceso administrativo a través de interfaces basadas en navegador e interfaces de programación de aplicaciones (API). | B39: 2
A40: 2.3 Los entornos inalámbricos se configuran y administran de forma segura.
A41: 2.3.1 Para entornos inalámbricos conectados al CDE o que transmiten datos de tarjetahabientes, todos los valores predeterminados de los proveedores inalámbricos se cambian en la instalación o se confirma que son seguros, incluidos, entre otros: • Claves de cifrado inalámbricas predeterminadas. • Contraseñas o puntos de acceso inalámbricos. • Valores predeterminados de SNMP, • Cualquier otro proveedor inalámbrico predeterminado relacionado con la seguridad. Notas de Aplicabilidad Esto incluye, pero no se limita a, las claves de encriptación inalámbrica predeterminadas, las contraseñas de los puntos de acceso inalámbricos, los valores predeterminados de SNMP y cualquier otro valor predeterminado del proveedor inalámbrico relacionado con la seguridad. | B41: 2
A42: 2.3.2 Para los entornos inalámbricos conectados al CDE o que transmitan datos de tarjetahabientes, las claves cifradas inalámbricas se cambian como sigue: • Siempre que el personal con conocimiento de la clave deje la empresa o la función para la que era necesario el conocimiento. • Siempre que se sospeche o se sepa que una clave está comprometida. | B42: 2
A43: Requisito 3: Proteger los Datos de Tarjetahabientes Almacenados
A44: 3.1 Se definen y comprenden los procesos y mecanismos para realizar las actividades del Requisito 3.
A45: 3.1.1 Todas las políticas de seguridad y procedimientos operativos que se identifican en el Requisito 3 son: • Documentados. • Actualizados. • En uso. • Conocidos por todas las partes involucradas. | B45: 6
A46: 3.1.2 Los roles y responsabilidades para realizar las actividades del Requisito 3 están documentados, asignados y comprendidos. Nuevo requisito - efectivo inmediatamente | B46: 6
A47: 3.2 El almacenamiento de los datos de tarjetahabientes se mantiene al mínimo.
A48: 3.2.1 El almacenamiento de datos de tarjetahabientes se mantiene al mínimo mediante la implementación de políticas y procedimientos de retención y eliminación de datos que incluyan al menos lo siguiente: • Cubren todas las ubicaciones donde hay datos de tarjetahabientes. • Cubren todo dato confidencial de autenticación (SAD) almacenado antes de completar la autorización. Este punto es la mejor práctica hasta su fecha de vigencia; consulte las Notas de Aplicabilidad que aparecen a continuación para obtener más detalles. • Limitar la cantidad de datos almacenados y su tiempo de retención a lo requerido por los requisitos legales o reglamentarios y/o de negocios. • Requisitos de retención específicos para los datos de tarjetahabientes que definen la duración del período de retención e incluyen una justificación de negocio documentada. • Procesos para el borrado seguro o para hacer que los datos de tarjetahabiente sean irrecuperables cuando ya no se necesitan según la política de retención. • Un proceso para verificar, al menos una vez cada tres meses, que los datos de tarjetahabientes que excedan el período de retención definido se han eliminado de forma segura o se han vuelto irrecuperables. Notas de Aplicabilidad Cuando un TPSP almacena datos de tarjetahabientes (por ejemplo, en un entorno de nube), las entidades son responsables de trabajar con sus proveedores de servicios para comprender cómo el TPSP cumple con este requisito para la entidad. Las consideraciones incluyen garantizar que todas las instancias geográficas de un elemento de datos se eliminen de forma segura. El punto anterior (para la cobertura de SAD almacenada antes de completar la autorización) es la mejor práctica hasta el 31 de marzo de 2025, después de lo cual se requerirá como parte del Requisito 3.2.1 y se debe considerar en su totalidad durante una evaluación de los PCI DSS. | B48: 1
A49: 3.3 Los datos confidenciales de autenticación (SAD) no se almacenan después de la autorización.
A50: 3.3.1 Los SAD no se retienen después de la autorización, incluso si están cifrados. Todos los datos confidenciales de autenticación recibidos se vuelven irrecuperables una vez finalizado el proceso de autorización Notas de Aplicabilidad Este requisito no se aplica a los emisores y empresas que apoyan los servicios de emisión (en los que los SAD son requeridos para una necesidad legítima de negocio de emisión) y tienen una justificación de negocio para almacenar los datos confidenciales de autenticación. Consulte el Requisito 3.3.3 para conocer los requisitos adicionales específicos para emisores. Los datos confidenciales de autenticación incluyen los datos citados en los Requisitos 3.3.1.1 hasta el 3.3.1.3. | B50: 1
A51: 3.3.1.1 El contenido completo de cualquier pista no se conserva una vez finalizado el proceso de autorización. Notas de Aplicabilidad En el curso normal de los negocios, es posible que sea necesario conservar los siguientes elementos de datos de la pista: • Nombre del tarjetahabiente. • Número de cuenta principal (PAN). • Fecha de expiración. • Código de servicio. Para minimizar el riesgo, almacene de forma segura sólo estos elementos de datos según sea necesario para la empresa. | B51: 1
A52: 3.3.1.2 El código de verificación de la tarjeta no se conserva una vez finalizado el proceso de autorización. Notas de Aplicabilidad El código de verificación de la tarjeta es el número de tres o cuatro dígitos impreso en el anverso o el reverso de una tarjeta de pago y que se utiliza para verificar las transacciones no presenciales de la tarjeta. | B52: 1
A53: 3.3.1.3 El número de identificación personal (PIN) y el bloque del PIN no se conservan al finalizar el proceso de autorización. Notas de Aplicabilidad Los bloques PIN se cifran durante el curso natural de los procesos de transacción, pero incluso si una entidad cifra el bloque de PIN nuevamente, todavía no se permite que se almacene después de la finalización del proceso de autorización. | B53: 1
A54: 3.3.2 Los SAD que se almacenan electrónicamente antes de completar la autorización se cifran mediante criptografía robusta. Notas de Aplicabilidad Las organizaciones que administran los programas de conformidad (por ejemplo, las marcas de pago y adquirentes) determinan si se permite el almacenamiento de los SAD antes de la autorización. Comuníquese con las organizaciones de interés para cualquier criterio adicional. Este requisito aplica para todo almacenamiento de los SAD, incluso si no hay datos PAN en el entorno. Consulte el Requisito 3.2.1 para conocer el requisito adicional que aplica si el SAD se almacena antes de completar la autorización. Este requisito no aplica para los emisores y empresas que apoyan la emisión de servicios cuando existe una justificación comercial legítima de emisión para almacenar los SAD). Consulte el Requisito 3.3.3 para conocer los requisitos específicos para emisores. Este requisito no reemplaza la forma en que se deben administrar los bloques PIN ni significa que aquellos que hayan sido debidamente cifrados necesiten cifrarse nuevamente. Este requisito es la mejor práctica recomendada hasta el 31 de marzo de 2025, después de lo cual será obligatorio y debe tenerse en cuenta en su totalidad durante una evaluación PCI DSS. | B54: 1
A55: 3.3.3 Requisito adicional para emisores y empresas que apoyan servicios de emisión y que almacenan datos confidenciales de autenticación: Cualquier almacenamiento de datos confidenciales de autenticación está: • Limitado a lo que se necesita para una necesidad legítima de negocio de emisión y está asegurado. • Cifrado utilizando criptografía robusta. Notas de Aplicabilidad Este requisito se aplica solo para los emisores y empresas que apoyan la emisión de servicios y almacenan datos confidenciales de autenticación. Las entidades que emiten tarjetas de pago o que realizan o apoyan servicios de emisión a menudo crearán y controlarán datos confidenciales de autenticación como parte de la función de emisión. Está permitido a las empresas que realizan, facilitan o apoyan servicios de emisión, almacenar datos confidenciales de autenticación SÓLO SI se tiene una necesidad legítima de negocio de almacenar dichos datos. Los requisitos PCI DSS están destinados a todas las entidades que almacenan, procesan o transmiten datos de tarjetahabientes, incluidos los emisores. La única excepción para los emisores y procesadores de emisores es que los datos confidenciales de autenticación pueden retenerse si existe una razón legítima para hacerlo. Estos datos deben almacenarse de forma segura y de acuerdo con todas PCI DSS y los requisitos específicos de la marca de pago. (continúa en la página siguiente) El punto anterior (para cifrar los SAD almacenados con criptografía robusta) es la mejor práctica hasta el 31 de marzo de 2025, después de lo cual se requerirá como parte del Requisito 3.3.3 y se debe considerar por completo durante una evaluación PCI DSS. | B55: 1
A56: 3.4 El acceso a las pantallas de datos PAN completas y la capacidad de copiar los datos de tarjetahabientes está restringidos.
A57: 3.4.1 Los datos PAN están enmascarados cuando se muestra (el BIN y los últimos cuatro dígitos constituyen el número máximo de dígitos que se muestran), de manera que sólo el personal con una necesidad legítima de negocios pueda ver más que el BIN y los últimos cuatro dígitos de los datos PAN. Notas de Aplicabilidad Este requisito no sustituye a otros más estrictos para la visualización de los datos de tarjetahabientes, por ejemplo, los requisitos legales o de las marcas de pago para los recibos de los puntos de venta (POS). Este requisito se refiere a la protección de los datos PAN cuando se muestran en pantallas, recibos de papel, impresiones, etc., y no debe confundirse con el requisito 3.5.1 para la protección de los datos PAN cuando se almacenan, se procesan o se transmiten. | B57: 5
A58: 3.4.2 Cuando se utilicen tecnologías de acceso remoto los controles técnicos impiden la copia y/o la reubicación de los datos PAN para todo el personal, excepto para aquellos con autorización explícita y documentada y una necesidad legítima de negocio y definida. Notas de Aplicabilidad Almacenar o reubicar los datos PAN en discos duros locales, medios electrónicos extraíbles y otros dispositivos de almacenamiento hace que estos dispositivos estén dentro del alcance PCI DSS. Este requisito es la mejor práctica recomendada hasta el 31 de marzo de 2025, después de lo cual será obligatorio y debe tenerse en cuenta en su totalidad durante una evaluación PCI DSS. | B58: 5
A59: 3.5 El número de cuenta principal (PAN) está protegido donde sea que se almacene.
A60: 3.5.1 Los datos PAN se hace ilegible en cualquier lugar donde se almacene utilizando cualquiera de los siguientes enfoques: • Hashes unidireccionales basados en criptografía robusta del PAN completo. • Truncamiento (los hashes no pueden utilizarse para reemplazar el segmento truncado de la PAN). • Índice de tokens. • Criptografía robusta con procesos y procedimientos de gestión de claves asociados. • Si en un entorno hay versiones truncadas y con hash del mismo PAN, o diferentes formatos de truncamiento del mismo PAN, se establecen controles adicionales de manera que las diferentes versiones no puedan correlacionarse para reconstruir el PAN original. Notas de Aplicabilidad Constituye un esfuerzo relativamente trivial para individuos malintencionados el reconstruir los datos del PAN originales si tienen acceso tanto a la versión truncada como a la versión hash de un PAN. Este requisito se aplica a los datos PAN guardados en almacenamiento primario (bases de datos o archivos planos como hojas de cálculo de archivos de texto), así como en almacenamiento no primario (copias de seguridad, registros de auditoría, registros de excepciones o de resolución de problemas), todos ellos deben estar protegidos. Este requisito no excluye el uso de archivos temporales que contengan datos PAN en texto no cifrado mientras se encriptan y desencriptan. | B60: 5
A61: 3.5.1.1 Los hash utilizados para hacer ilegibles los datos PAN (según el primer punto del requisito 3.5.1) son hashes criptográficos con clave de todos los datos PAN, con procesos y procedimientos de gestión de claves asociados de acuerdo con los Requisitos 3.6 y 3.7. Notas de Aplicabilidad Este requisito se aplica a los datos PAN guardados en almacenamiento primario (bases de datos o archivos planos como hojas de cálculo de archivos de texto), así como en almacenamiento no primario (copias de seguridad, registros de auditoría, registros de excepciones o de resolución de problemas), todos ellos deben estar protegidos. Este requisito no excluye el uso de archivos temporales que contengan datos PAN en texto no cifrado mientras se encriptan y desencriptan. Este requisito se considera una práctica recomendada hasta el 31 de marzo de 2025, después de lo cual será obligatorio y debe tenerse en cuenta en su totalidad durante una evaluación PCI DSS. | B61: 5
A62: 3.5.1.2 Si se utiliza un cifrado a nivel de disco o de partición (en lugar de un cifrado de base de datos a nivel de archivo, columna o campo) para hacer que los datos PAN sea ilegibles, sólo se implementará de la siguiente manera: • En medios electrónicos extraíbles O • Si se utiliza para medios electrónicos no extraíbles, los datos PAN también se hacen ilegibles mediante otro mecanismo que cumpla con el Requisito 3.5.1. Nota: Las implementaciones de cifrado de discos o particiones también deben cumplir todos los demás requisitos de cifrado y gestión de claves PCI DSS. Notas de Aplicabilidad Aunque el cifrado de disco puede seguir estando presente en estos tipos de dispositivos, este no puede ser el único mecanismo utilizado para proteger los datos PAN almacenadas en esos sistemas. Cualquier dato del PAN almacenado también debe volverse ilegible según el Requisito 3.5.1, por ejemplo, mediante el truncamiento o por un mecanismo de cifrado a nivel de datos. El cifrado de disco completo ayuda a proteger los datos en caso de pérdida física de un disco y, por lo tanto, su uso es apropiado sólo para dispositivos de almacenamiento de medios electrónicos extraíbles. Los medios que forman parte de la arquitectura de un centro de datos (por ejemplo, unidades intercambiables en caliente, copias de seguridad en cinta) se consideran medios electrónicos no extraíbles a los que se aplica el Requisito 3.5.1. Las implementaciones de cifrado de discos o particiones también deben cumplir todos los demás requisitos de cifrado y gestión de claves PCI DSS. Este requisito es la mejor práctica recomendada hasta el 31 de marzo de 2025, después de lo cual será obligatorio y debe tenerse en cuenta en su totalidad durante una evaluación PCI DSS. | B62: 5
A63: 3.5.1.3 Si se utiliza el cifrado a nivel del disco o de partición (en lugar del cifrado de la base de datos a nivel de archivo, columna o campo) para hacer que los datos PAN sea ilegibles, sólo se implementará de la siguiente manera: • El acceso lógico se gestiona por separado e independientemente de la autenticación del sistema operativo nativo y de los mecanismos de control de acceso. • Las claves de descifrado no están asociadas a las cuentas de usuarios. • Los factores de autenticación (contraseñas, frases de paso o claves criptográficas) que permiten el acceso a los datos no cifrados se almacenan de forma segura. Notas de Aplicabilidad Las implementaciones de cifrado de discos o particiones también deben cumplir todos los demás requisitos de cifrado y gestión de claves PCI DSS. | B63: 5
A64: 3.6 Las claves criptográficas utilizadas para proteger los datos almacenados de tarjetahabientes están protegidos.
A65: 3.6.1 Los procedimientos se definen e implementan para proteger las claves cifradas utilizadas para proteger los datos almacenados de tarjetahabientes contra la divulgación y el uso indebido que incluyen: • El acceso a las claves está restringido al menor número de custodios necesarios. • Las claves de cifrado de claves son al menos tan seguras como las claves de cifrado de datos que estas protegen. • Las claves de cifrado de claves se almacenan por separado de las claves de cifrado de datos. • Las claves se almacenan de forma segura en el menor número posible de formas y ubicaciones. Notas de Aplicabilidad Este requisito se aplica a las claves utilizadas para cifrar los datos almacenados de tarjetahabientes y a las claves de cifrado utilizadas para proteger las claves de cifrado de datos. El requisito para proteger las claves utilizadas para proteger los datos almacenados de tarjetahabientes de la divulgación y el uso indebido se aplica tanto a las claves de cifrado de datos como a las claves de cifrado de claves. Debido a que una clave de cifrado de claves puede otorgar acceso a muchas claves de cifrado de datos, las claves de cifrado de claves requieren fuertes medidas de protección. | B65: 5
A66: 3.6.1.1 Requisito adicional sólo para proveedores de servicios: Se mantiene una descripción documentada de la arquitectura criptográfica que incluye: • Detalles de todos los algoritmos, protocolos y claves utilizados para la protección de los datos de tarjetahabientes, incluyendo la fuerza de la clave y la fecha de caducidad. • Evitar el uso de las mismas claves criptográficas en entornos de producción y de prueba. Este punto es la mejor práctica hasta su fecha de vigencia; consulte las Notas de Aplicabilidad que aparecen a continuación para obtener más detalles. • Descripción del uso de claves para cada clave. • Inventario de los módulos de seguridad de hardware (HSM), sistemas de gestión de claves (KMS) y otros dispositivos criptográficos seguros (SCD) utilizados para la gestión de claves, incluido el tipo y la ubicación de los dispositivos, como se describe en el Requisito 12.3.3. Notas de Aplicabilidad Este requisito se aplica solo cuando la entidad evaluada es un proveedor de servicios. En las implementaciones de HSM en la nube, la responsabilidad de la arquitectura criptográfica de acuerdo con este Requisito será compartida entre el proveedor de la nube y el cliente de la nube. El punto anterior (para que en la arquitectura criptográfica se impida el uso de las mismas claves criptográficas en producción y prueba) es una mejor práctica hasta el 31 de marzo de 2025, después de lo cual se requerirá como parte del Requisito 3.6.1.1 y deberá tenerse en cuenta en su totalidad durante una evaluación PCI DSS. | B66: 5
A67: 3.6.1.2 Las claves secretas y privadas que se utilizan para cifrar/descifrar los datos de tarjetahabientes se almacenan en uno (o más) de los siguientes formularios en todo momento: • Cifrado con una clave de cifrado de clave, que sea al menos tan fuerte, como la clave de cifrado de datos y que se almacene por separado de la clave de cifrado de datos. • Dentro de un dispositivo criptográfico seguro (SCD), como un módulo de seguridad de hardware (HSM) o un dispositivo de punto de interacción aprobado por PTS. • Como mínimo dos componentes clave de longitud completa o recursos compartidos de clave, de acuerdo con un método aceptado por la industria. Notas de Aplicabilidad No es necesario que las claves públicas sean almacenadas en uno de estas formas. Las claves criptográficas almacenadas como parte de un sistema de gestión de claves (KMS) que emplea SCD son aceptables. Una clave criptográfica que se divide en dos partes no cumple con este requisito. Las claves secretas o privadas almacenadas como componentes clave o recursos compartidos de claves deben generarse a través de uno de los siguientes métodos: • Utilizando un generador de números aleatorios aprobado y dentro de un SCD, O • De acuerdo con el estándar ISO 19592 o su equivalente en la industria para la generación de claves secretas compartidas. | B67: 5
A68: 3.6.1.3 El acceso a los componentes de claves criptográficas de texto no cifrado está restringido al menor número posible de custodios que sean necesarios. | B68: 5
A69: 3.6.1.4 Las claves criptográficas se almacenan en el menor número posible de ubicaciones. | B69: 5
A70: 3.7 Cuando se usa criptografía para proteger datos almacenados de tarjetahabientes, se definen e implementan procesos y procedimientos de administración de claves que cubren todos los aspectos del ciclo de vida de las claves.
A71: 3.7.1 Las políticas y procedimientos de administración de claves se implementan para incluir la generación de claves criptográficas fuertes utilizadas para proteger los datos almacenados de los tarjetahabientes. | B71: 5
A72: 3.7.2 Las políticas y los procedimientos de administración de claves son implementados para incluir la distribución segura de las claves criptográficas utilizadas para proteger los datos almacenados de tarjetahabientes. | B72: 5
A73: 3.7.3 Se implementan políticas y procedimientos de gestión de claves para incluir el almacenamiento seguro de las claves criptográficas utilizadas para proteger los datos de tarjetahabientes almacenado. | B73: 5
A74: 3.7.4 Se implementan políticas y procedimientos de gestión de claves para los cambios de claves criptográficas de para aquellas claves que han llegado al final de su criptoperíodo, según lo definido por el proveedor de la aplicación asociada o el propietario de la clave, y basado en las mejores prácticas y directrices de la industria, incluyendo lo siguiente: • Un criptoperíodo definido para cada tipo de clave en uso. • Un proceso para el cambio de claves al final del criptoperíodo definido. | B74: 5
A75: 3.7.5 Los procedimientos de políticas de gestión de claves se implementan para incluir el retiro, sustitución o destrucción de las claves utilizadas para proteger los datos almacenados de tarjetahabientes, según se considere necesario cuando: • La clave haya llegado al final de su criptoperíodo definido. • La integridad de la clave se haya debilitado, incluso cuando el personal con conocimiento de un componente de la clave en texto no cifrado abandone la empresa, o la función por la que conocía la clave. • Cuando se sospecha o se sabe que las claves están comprometidas. Las claves retiradas o reemplazadas no se utilizan para operaciones de cifrado. Notas de Aplicabilidad Si es necesario conservar las claves criptográficas retiradas o reemplazas, dichas claves deben archivarse de forma segura (por ejemplo, utilizando una clave de cifrado). | B75: 5
A76: 3.7.6 Cuando el personal realiza operaciones manuales de gestión de claves criptográficas en texto no cifrado, se implementan políticas y procedimientos de gestión de claves que incluyen la gestión de estas operaciones utilizando conocimiento dividido y control dual. Notas de Aplicabilidad Este control es aplicable para operaciones manuales de administración de claves o donde la administración de claves no está controlada por el producto de cifrado. Una clave criptográfica que simplemente se divide en dos partes no cumple con este requisito. Las claves secretas o privadas almacenadas como componentes clave o recursos compartidos de claves deben generarse a través de uno de los siguientes métodos: • Utilizando un generador de números aleatorios aprobado y dentro de un dispositivo criptográfico seguro (SCD), como un módulo de seguridad de hardware (HSM) o un dispositivo de punto de interacción aprobado por PTS, O • De acuerdo con el estándar ISO 19592 o su equivalente en la industria para la generación de claves secretas compartidas. | B76: 5
A77: 3.7.7 Se implementan políticas y procedimientos de administración de claves para incluir la prevención de la sustitución no autorizada de claves criptográficas. | B77: 5
A78: 3.7.8 Las políticas y los procedimientos de administración de claves se implementan para incluir que los custodios de claves criptográficas reconozcan formalmente (por escrito o electrónicamente) que comprenden y aceptan sus responsabilidades como custodios de claves. | B78: 5
A79: 3.7.9 Requisito adicional sólo para proveedores de servicios: Cuando un proveedor de servicios comparte claves criptográficas con sus clientes para la transmisión o el almacenamiento de datos del tarjetahabiente, se documenta y distribuye a los clientes de los proveedores de servicios orientación sobre la transmisión, el almacenamiento y la actualización segura de dichas claves. Notas de Aplicabilidad Este requisito se aplica solo cuando la entidad que se evalúa es un proveedor de servicios. | B79: 5
A80: Requisito 4: Proteja los Datos de Tarjetahabientes con una Criptografía Robusta Durante la Transmisión
A81: 4.1 Se definen y documentan los procesos y mecanismos para realizar las actividades del Requisito 4.
A82: 4.1.1 Todas las políticas de seguridad y procedimientos operativos que se identifican en el Requisito 4 son: • Documentados • Actualizados • En uso • Conocidos por todas las partes involucradas | B82: 6
A83: 4.1.2 Los roles y responsabilidades para realizar las actividades del Requisito 4 están documentados, asignados y comprendidos. Nuevo requisito - efectivo inmediatamente | B83: 6
A84: 4.2 Los datos PAN está protegidos con criptografía robusta durante la transmisión.
A85: 4.2.1 Se implementan fuertes protocolos de seguridad y criptografía robusta de la siguiente manera para proteger los datos PAN durante la transmisión a través de redes públicas abiertas: • Sólo se aceptan claves y certificados confiables. • Los certificados utilizados para proteger los datos PAN durante la transmisión a través de redes públicas abiertas se confirman como válidos y no están vencidos ni revocados. Este punto es la mejor práctica hasta su fecha de vigencia; consulte las Notas de Aplicabilidad a continuación para obtener más detalles. • El protocolo en uso sólo apoya versiones o configuraciones seguras y no apoya el uso de versiones, algoritmos, tamaños de clave o implementaciones inseguras. • La fuerza del cifrado es apropiada para la metodología de cifrado en uso. Notas de Aplicabilidad Puede haber casos en los que una entidad reciba datos de tarjetahabientes no solicitados a través de un canal de comunicación inseguro que no fue diseñado con el propósito de recibir datos confidenciales. Ante esta situación, la entidad puede optar por incluir el canal en su CDE y asegurarlo de acuerdo con PCI DSS o implementar medidas para impedir que el canal se utilice para datos de tarjetahabientes. Un certificado auto-firmado también puede ser aceptable si el certificado es emitido por una CA interna dentro de la organización, si el autor del certificado está confirmado y si el certificado está verificado (por ejemplo, mediante hash o firma) y no está caducado. Hay que tomar en cuenta que los certificados auto-firmados en los que en el campo de Denominación Distinguida (DN) bajo "emitido por" y "emitido para" aparece la misma información, no son aceptables. El punto anterior (para confirmar que los certificados utilizados para proteger los datos PAN durante la transmisión a través de redes públicas abiertas son válidos y no están vencidos ni revocados) es una mejor práctica hasta el 31 de marzo de 2025, después de lo cual se requerirá como parte del Requisito 4.2.1 y debe tenerse en cuenta en su totalidad durante una evaluación PCI DSS. | B85: 2
A86: 4.2.1.1 Se mantiene un inventario de las claves y certificados confiables de la entidad utilizados para proteger los datos PAN durante la transmisión. Notas de Aplicabilidad Este requisito es la mejor práctica recomendada hasta el 31 de marzo de 2025, después de lo cual será obligatorio y debe tenerse en cuenta en su totalidad durante una evaluación de PCI DSS. | B86: 2
A87: 4.2.1.2 Las redes inalámbricas que transmiten datos PAN o están conectadas al CDE utilizan las mejores prácticas de la industria para implementar criptografía robusta para autenticación y transmisión. | B87: 2
A88: 4.2.2 Los datos PAN están protegidos con criptografía robusta siempre que se envíen a través de tecnologías de mensajería del usuario final. Notas de Aplicabilidad Este requisito también se aplica si un cliente u otro tercero solicitan que se le envíen datos PAN a través de tecnologías de mensajería para el usuario final. Puede haber casos en los que una entidad reciba datos no solicitados de tarjetahabientes a través de un canal de comunicación inseguro que no está destinado a la transmisión de datos confidenciales. Ante esta situación, la entidad puede optar por incluir el canal en su CDE y asegurarlo de acuerdo con PCI DSS o borrar los datos del tarjetahabiente e implementar medidas para impedir que el canal se utilice para datos de tarjetahabientes. | B88: 2
A89: Requisito 5: Proteger Todos los Sistemas y Redes de Software Malicioso
A90: 5.1 Se definen y comprenden los procesos y mecanismos para proteger todos los sistema y redes del software malintencionado.
A91: 5.1.1 Todas las políticas de seguridad y procedimientos operativos que se identifican en el Requisito 5 son: • Documentados • Actualizados • En uso • Conocidos por todas las partes involucradas | B91: 6
A92: 5.1.2 Los roles y responsabilidades para realizar las actividades del Requisito 5 están documentados, asignados y comprendidos. Nuevo requisito - efectivo inmediatamente | B92: 6
A93: 5.2 El software malintencionado (malware) es evadido, o se detecta y se soluciona.
A94: 5.2.1 Una solución antimalware se aplicará a todos los componentes del sistema, excepto a aquellos componentes del sistema identificados en evaluaciones periódicas según el Requisito 5.2.3 que concluye que los componentes del sistema no están en riesgo de malware. | B94: 2
A95: 5.2.2 Las soluciones antimalware implementadas: • Detectan todos los tipos conocidos de malware. • Eliminan, bloquean o contienen todos los tipos conocidos de malware. | B95: 2
A96: 5.2.3 Todos los componentes del sistema que no se encuentren en riesgo de malware se evalúan periódicamente para incluir lo siguiente: • Una lista documentada de todos los componentes del sistema que no están en riesgo de malware. • Identificación y evaluación de amenazas de malware en evolución para los componentes del sistema. • Confirmación de si dichos componentes del sistema continúan sin requerir protección antimalware. Notas de Aplicabilidad Los componentes del sistema cubiertos por este requisito son aquellos para los que no existe una solución antimalware implementada según el Requisito 5.2.1. | B96: 2
A97: 5.2.3.1 La frecuencia de las evaluaciones periódicas de los componentes del sistema identificados como no en riesgo de malware se define en el análisis de riesgo específico de la entidad, el cual se realiza de acuerdo con todos los elementos especificados en el Requisito 12.3.1. Notas de Aplicabilidad Este requisito es la mejor práctica recomendada hasta el 31 de marzo de 2025, después de lo cual será obligatorio y debe tenerse en cuenta en su totalidad durante una evaluación PCI DSS. | B97: 2
A98: 5.3 Los mecanismos y procesos antimalware están activos, mantenidos y monitoreados.
A99: 5.3.1 Las soluciones antimalware se mantienen actualizadas a través de procesos de actualización automáticos. | B99: 2
A100: 5.3.2 Soluciones antimalware: • Realizan escaneos periódicos y escaneos activos o en tiempo real O • Realizan un análisis continuo del comportamiento de los sistemas o procesos. | B100: 2
...

Sheet Calcs
A1: 1 | B1: 2 | C1: 3 | D1: 4 | E1: 5 | F1: 6 | G1: Total | H1: 1 - n/a | I1: 2 - n/a | J1: 3 - n/a | K1: 4 - n/a | L1: 5 - n/a | M1: 6 - n/a | N1: Total | P1: Date Value Detector re: Milestone 1 | Q1: Date Value Detector re: Milestone 2 | R1: Date Value Detector re: Milestone 3 | S1: Date Value Detector re: Milestone 4 | T1: Date Value Detector re: Milestone 5 | U1: Date Value Detector re: Milestone 6
P2: Milestone 1 Outstanding | Q2: Milestone 2 Outstanding | R2: Milestone 3 Outstanding | S2: Milestone 4 Outstanding | T2: Milestone 5 Outstanding | U2: Milestone 6 Outstanding | V2: Input Error Checker - "Yes" but still a date - Milestone 1 | W2: Input Error Checker - "Yes" but still a date - Milestone 2 | X2: Input Error Checker - "Yes" but still a date - Milestone 3 | Y2: Input Error Checker - "Yes" but still a date - Milestone 4 | Z2: Input Error Checker - "Yes" but still a date - Milestone 5 | AA2: Input Error Checker - "Yes" but still a date - Milestone 6 | AB2: Input Error Checker - "No" but no date - Milestone 1 | AC2: Input Error Checker - "No" but no date - Milestone 2 | AD2: Input Error Checker - "No" but no date - Milestone 3 | AE2: Input Error Checker - "No" but no date - Milestone 4 | AF2: Input Error Checker - "No" but no date - Milestone 5 | AG2: Input Error Checker - "No" but no date - Milestone 6
A4: =COUNTIFS('Hitos del Enfoque Prioritario'!B5,"1",'Hitos del Enfoque Prioritario'!C5,'Data Validation'!$A$2) -> 0 | B4: =COUNTIFS('Hitos del Enfoque Prioritario'!B5,"2",'Hitos del Enfoque Prioritario'!C5,'Data Validation'!$A$2) -> 0 | C4: =COUNTIFS('Hitos del Enfoque Prioritario'!B5,"3",'Hitos del Enfoque Prioritario'!C5,'Data Validation'!$A$2) -> 0 | D4: =COUNTIFS('Hitos del Enfoque Prioritario'!B5,"4",'Hitos del Enfoque Prioritario'!C5,'Data Validation'!$A$2) -> 0 | E4: =COUNTIFS('Hitos del Enfoque Prioritario'!B5,"5",'Hitos del Enfoque Prioritario'!C5,'Data Validation'!$A$2) -> 0 | F4: =COUNTIFS('Hitos del Enfoque Prioritario'!B5,"6",'Hitos del Enfoque Prioritario'!C5,'Data Validation'!$A$2) -> 0 | G4: =SUM(A4:F4) -> 0 | H4: =COUNTIFS('Hitos del Enfoque Prioritario'!B5,"1",'Hitos del Enfoque Prioritario'!C5,'Data Validation'!$A$4) -> 0 | I4: =COUNTIFS('Hitos del Enfoque Prioritario'!B5,"2",'Hitos del Enfoque Prioritario'!C5,'Data Validation'!$A$4) -> 0 | J4: =COUNTIFS('Hitos del Enfoque Prioritario'!B5,"3",'Hitos del Enfoque Prioritario'!C5,'Data Validation'!$A$4) -> 0 | K4: =COUNTIFS('Hitos del Enfoque Prioritario'!B5,"4",'Hitos del Enfoque Prioritario'!C5,'Data Validation'!$A$4) -> 0 | L4: =COUNTIFS('Hitos del Enfoque Prioritario'!B5,"5",'Hitos del Enfoque Prioritario'!C5,'Data Validation'!$A$4) -> 0 | M4: =COUNTIFS('Hitos del Enfoque Prioritario'!B5,"6",'Hitos del Enfoque Prioritario'!C5,'Data Validation'!$A$4) -> 0 | N4: =SUM(H4:M4) -> 0 | P4: =IF('Hitos del Enfoque Prioritario'!$B5=1,'Hitos del Enfoque Prioritario'!$F5,"") | Q4: =IF('Hitos del Enfoque Prioritario'!$B5=2,'Hitos del Enfoque Prioritario'!$F5,"") | R4: =IF('Hitos del Enfoque Prioritario'!$B5=3,'Hitos del Enfoque Prioritario'!$F5,"") | S4: =IF('Hitos del Enfoque Prioritario'!$B5=4,'Hitos del Enfoque Prioritario'!$F5,"") | T4: =IF('Hitos del Enfoque Prioritario'!$B5=5,'Hitos del Enfoque Prioritario'!$F5,"") | U4: =IF('Hitos del Enfoque Prioritario'!$B5=6,'Hitos del Enfoque Prioritario'!$F5,"") -> 0 | V4: =IF(AND('Hitos del Enfoque Prioritario'!C5='Data Validation'!$A$2,'Hitos del Enfoque Prioritario'!F5=""),"CORRECT",IF('Hitos del Enfoque Prioritario'!C5='Data Validation'!$A$3,"CORRECT",IF('Hitos del Enfoque Prioritario'!B5=1,"ERROR 1",'Data Validation'!$A$4))) -> N/A | W4: =IF(AND('Hitos del Enfoque Prioritario'!C5='Data Validation'!$A$2,'Hitos del Enfoque Prioritario'!F5=""),"CORRECT",IF('Hitos del Enfoque Prioritario'!C5='Data Validation'!$A$3,"CORRECT",IF('Hitos del Enfoque Prioritario'!B5=2,"ERROR 1",'Data Validation'!$A$4))) -> N/A | X4: =IF(AND('Hitos del Enfoque Prioritario'!C5='Data Validation'!$A$2,'Hitos del Enfoque Prioritario'!F5=""),"CORRECT",IF('Hitos del Enfoque Prioritario'!C5='Data Validation'!$A$3,"CORRECT",IF('Hitos del Enfoque Prioritario'!B5=3,"ERROR 1",'Data Validation'!$A$4))) -> N/A | Y4: =IF(AND('Hitos del Enfoque Prioritario'!C5='Data Validation'!$A$2,'Hitos del Enfoque Prioritario'!F5=""),"CORRECT",IF('Hitos del Enfoque Prioritario'!C5='Data Validation'!$A$3,"CORRECT",IF('Hitos del Enfoque Prioritario'!B5=4,"ERROR 1",'Data Validation'!$A$4))) -> N/A | Z4: =IF(AND('Hitos del Enfoque Prioritario'!C5='Data Validation'!$A$2,'Hitos del Enfoque Prioritario'!F5=""),"CORRECT",IF('Hitos del Enfoque Prioritario'!C5='Data Validation'!$A$3,"CORRECT",IF('Hitos del Enfoque Prioritario'!B5=5,"ERROR 1",'Data Validation'!$A$4))) -> N/A | AA4: =IF(AND('Hitos del Enfoque Prioritario'!C5='Data Validation'!$A$2,'Hitos del Enfoque Prioritario'!F5=""),"CORRECT",IF('Hitos del Enfoque Prioritario'!C5='Data Validation'!$A$3,"CORRECT",IF('Hitos del Enfoque Prioritario'!B5=6,"ERROR 1",'Data Validation'!$A$4))) -> ERROR 1 | AB4: =IF(AND('Hitos del Enfoque Prioritario'!C5='Data Validation'!$A$3,'Hitos del Enfoque Prioritario'!F5=""),IF('Hitos del Enfoque Prioritario'!B5=1,"ERROR 2",'Data Validation'!$A$4),"CORRECT") -> CORRECT | AC4: =IF(AND('Hitos del Enfoque Prioritario'!C5='Data Validation'!$A$3,'Hitos del Enfoque Prioritario'!F5=""),IF('Hitos del Enfoque Prioritario'!B5=2,"ERROR 2",'Data Validation'!$A$4),"CORRECT") -> CORRECT | AD4: =IF(AND('Hitos del Enfoque Prioritario'!C5='Data Validation'!$A$3,'Hitos del Enfoque Prioritario'!F5=""),IF('Hitos del Enfoque Prioritario'!B5=3,"ERROR 2",'Data Validation'!$A$4),"CORRECT") -> CORRECT | AE4: =IF(AND('Hitos del Enfoque Prioritario'!C5='Data Validation'!$A$3,'Hitos del Enfoque Prioritario'!F5=""),IF('Hitos del Enfoque Prioritario'!B5=4,"ERROR 2",'Data Validation'!$A$4),"CORRECT") -> CORRECT | AF4: =IF(AND('Hitos del Enfoque Prioritario'!C5='Data Validation'!$A$3,'Hitos del Enfoque Prioritario'!F5=""),IF('Hitos del Enfoque Prioritario'!B5=5,"ERROR 2",'Data Validation'!$A$4),"CORRECT") -> CORRECT | AG4: =IF(AND('Hitos del Enfoque Prioritario'!C5='Data Validation'!$A$3,'Hitos del Enfoque Prioritario'!F5=""),IF('Hitos del Enfoque Prioritario'!B5=6,"ERROR 2",'Data Validation'!$A$4),"CORRECT") -> CORRECT
A5: =COUNTIFS('Hitos del Enfoque Prioritario'!B6,"1",'Hitos del Enfoque Prioritario'!C6,'Data Validation'!$A$2) -> 0 | B5: =COUNTIFS('Hitos del Enfoque Prioritario'!B6,"2",'Hitos del Enfoque Prioritario'!C6,'Data Validation'!$A$2) -> 0 | C5: =COUNTIFS('Hitos del Enfoque Prioritario'!B6,"3",'Hitos del Enfoque Prioritario'!C6,'Data Validation'!$A$2) -> 0 | D5: =COUNTIFS('Hitos del Enfoque Prioritario'!B6,"4",'Hitos del Enfoque Prioritario'!C6,'Data Validation'!$A$2) -> 0 | E5: =COUNTIFS('Hitos del Enfoque Prioritario'!B6,"5",'Hitos del Enfoque Prioritario'!C6,'Data Validation'!$A$2) -> 0 | F5: =COUNTIFS('Hitos del Enfoque Prioritario'!B6,"6",'Hitos del Enfoque Prioritario'!C6,'Data Validation'!$A$2) -> 0 | G5: =SUM(A5:F5) -> 0 | H5: =COUNTIFS('Hitos del Enfoque Prioritario'!B6,"1",'Hitos del Enfoque Prioritario'!C6,'Data Validation'!$A$4) -> 0 | I5: =COUNTIFS('Hitos del Enfoque Prioritario'!B6,"2",'Hitos del Enfoque Prioritario'!C6,'Data Validation'!$A$4) -> 0 | J5: =COUNTIFS('Hitos del Enfoque Prioritario'!B6,"3",'Hitos del Enfoque Prioritario'!C6,'Data Validation'!$A$4) -> 0 | K5: =COUNTIFS('Hitos del Enfoque Prioritario'!B6,"4",'Hitos del Enfoque Prioritario'!C6,'Data Validation'!$A$4) -> 0 | L5: =COUNTIFS('Hitos del Enfoque Prioritario'!B6,"5",'Hitos del Enfoque Prioritario'!C6,'Data Validation'!$A$4) -> 0 | M5: =COUNTIFS('Hitos del Enfoque Prioritario'!B6,"6",'Hitos del Enfoque Prioritario'!C6,'Data Validation'!$A$4) -> 0 | N5: =SUM(H5:M5) -> 0 | P5: =IF('Hitos del Enfoque Prioritario'!$B6=1,'Hitos del Enfoque Prioritario'!$F6,"") | Q5: =IF('Hitos del Enfoque Prioritario'!$B6=2,'Hitos del Enfoque Prioritario'!$F6,"") | R5: =IF('Hitos del Enfoque Prioritario'!$B6=3,'Hitos del Enfoque Prioritario'!$F6,"") | S5: =IF('Hitos del Enfoque Prioritario'!$B6=4,'Hitos del Enfoque Prioritario'!$F6,"") | T5: =IF('Hitos del Enfoque Prioritario'!$B6=5,'Hitos del Enfoque Prioritario'!$F6,"") | U5: =IF('Hitos del Enfoque Prioritario'!$B6=6,'Hitos del Enfoque Prioritario'!$F6,"") -> 0 | V5: =IF(AND('Hitos del Enfoque Prioritario'!C6='Data Validation'!$A$2,'Hitos del Enfoque Prioritario'!F6=""),"CORRECT",IF('Hitos del Enfoque Prioritario'!C6='Data Validation'!$A$3,"CORRECT",IF('Hitos del Enfoque Prioritario'!B6=1,"ERROR 1",'Data Validation'!$A$4))) -> N/A | W5: =IF(AND('Hitos del Enfoque Prioritario'!C6='Data Validation'!$A$2,'Hitos del Enfoque Prioritario'!F6=""),"CORRECT",IF('Hitos del Enfoque Prioritario'!C6='Data Validation'!$A$3,"CORRECT",IF('Hitos del Enfoque Prioritario'!B6=2,"ERROR 1",'Data Validation'!$A$4))) -> N/A | X5: =IF(AND('Hitos del Enfoque Prioritario'!C6='Data Validation'!$A$2,'Hitos del Enfoque Prioritario'!F6=""),"CORRECT",IF('Hitos del Enfoque Prioritario'!C6='Data Validation'!$A$3,"CORRECT",IF('Hitos del Enfoque Prioritario'!B6=3,"ERROR 1",'Data Validation'!$A$4))) -> N/A | Y5: =IF(AND('Hitos del Enfoque Prioritario'!C6='Data Validation'!$A$2,'Hitos del Enfoque Prioritario'!F6=""),"CORRECT",IF('Hitos del Enfoque Prioritario'!C6='Data Validation'!$A$3,"CORRECT",IF('Hitos del Enfoque Prioritario'!B6=4,"ERROR 1",'Data Validation'!$A$4))) -> N/A | Z5: =IF(AND('Hitos del Enfoque Prioritario'!C6='Data Validation'!$A$2,'Hitos del Enfoque Prioritario'!F6=""),"CORRECT",IF('Hitos del Enfoque Prioritario'!C6='Data Validation'!$A$3,"CORRECT",IF('Hitos del Enfoque Prioritario'!B6=5,"ERROR 1",'Data Validation'!$A$4))) -> N/A | AA5: =IF(AND('Hitos del Enfoque Prioritario'!C6='Data Validation'!$A$2,'Hitos del Enfoque Prioritario'!F6=""),"CORRECT",IF('Hitos del Enfoque Prioritario'!C6='Data Validation'!$A$3,"CORRECT",IF('Hitos del Enfoque Prioritario'!B6=6,"ERROR 1",'Data Validation'!$A$4))) -> ERROR 1 | AB5: =IF(AND('Hitos del Enfoque Prioritario'!C6='Data Validation'!$A$3,'Hitos del Enfoque Prioritario'!F6=""),IF('Hitos del Enfoque Prioritario'!B6=1,"ERROR 2",'Data Validation'!$A$4),"CORRECT") -> CORRECT | AC5: =IF(AND('Hitos del Enfoque Prioritario'!C6='Data Validation'!$A$3,'Hitos del Enfoque Prioritario'!F6=""),IF('Hitos del Enfoque Prioritario'!B6=2,"ERROR 2",'Data Validation'!$A$4),"CORRECT") -> CORRECT | AD5: =IF(AND('Hitos del Enfoque Prioritario'!C6='Data Validation'!$A$3,'Hitos del Enfoque Prioritario'!F6=""),IF('Hitos del Enfoque Prioritario'!B6=3,"ERROR 2",'Data Validation'!$A$4),"CORRECT") -> CORRECT | AE5: =IF(AND('Hitos del Enfoque Prioritario'!C6='Data Validation'!$A$3,'Hitos del Enfoque Prioritario'!F6=""),IF('Hitos del Enfoque Prioritario'!B6=4,"ERROR 2",'Data Validation'!$A$4),"CORRECT") -> CORRECT | AF5: =IF(AND('Hitos del Enfoque Prioritario'!C6='Data Validation'!$A$3,'Hitos del Enfoque Prioritario'!F6=""),IF('Hitos del Enfoque Prioritario'!B6=5,"ERROR 2",'Data Validation'!$A$4),"CORRECT") -> CORRECT | AG5: =IF(AND('Hitos del Enfoque Prioritario'!C6='Data Validation'!$A$3,'Hitos del Enfoque Prioritario'!F6=""),IF('Hitos del Enfoque Prioritario'!B6=6,"ERROR 2",'Data Validation'!$A$4),"CORRECT") -> CORRECT
A6: =COUNTIFS('Hitos del Enfoque Prioritario'!B7,"1",'Hitos del Enfoque Prioritario'!C7,'Data Validation'!$A$2) -> 0 | B6: =COUNTIFS('Hitos del Enfoque Prioritario'!B7,"2",'Hitos del Enfoque Prioritario'!C7,'Data Validation'!$A$2) -> 0 | C6: =COUNTIFS('Hitos del Enfoque Prioritario'!B7,"3",'Hitos del Enfoque Prioritario'!C7,'Data Validation'!$A$2) -> 0 | D6: =COUNTIFS('Hitos del Enfoque Prioritario'!B7,"4",'Hitos del Enfoque Prioritario'!C7,'Data Validation'!$A$2) -> 0 | E6: =COUNTIFS('Hitos del Enfoque Prioritario'!B7,"5",'Hitos del Enfoque Prioritario'!C7,'Data Validation'!$A$2) -> 0 | F6: =COUNTIFS('Hitos del Enfoque Prioritario'!B7,"6",'Hitos del Enfoque Prioritario'!C7,'Data Validation'!$A$2) -> 0 | G6: =SUM(A6:F6) -> 0 | H6: =COUNTIFS('Hitos del Enfoque Prioritario'!B7,"1",'Hitos del Enfoque Prioritario'!C7,'Data Validation'!$A$4) -> 0 | I6: =COUNTIFS('Hitos del Enfoque Prioritario'!B7,"2",'Hitos del Enfoque Prioritario'!C7,'Data Validation'!$A$4) -> 0 | J6: =COUNTIFS('Hitos del Enfoque Prioritario'!B7,"3",'Hitos del Enfoque Prioritario'!C7,'Data Validation'!$A$4) -> 0 | K6: =COUNTIFS('Hitos del Enfoque Prioritario'!B7,"4",'Hitos del Enfoque Prioritario'!C7,'Data Validation'!$A$4) -> 0 | L6: =COUNTIFS('Hitos del Enfoque Prioritario'!B7,"5",'Hitos del Enfoque Prioritario'!C7,'Data Validation'!$A$4) -> 0 | M6: =COUNTIFS('Hitos del Enfoque Prioritario'!B7,"6",'Hitos del Enfoque Prioritario'!C7,'Data Validation'!$A$4) -> 0 | N6: =SUM(H6:M6) -> 0 | P6: =IF('Hitos del Enfoque Prioritario'!$B7=1,'Hitos del Enfoque Prioritario'!$F7,"") | Q6: =IF('Hitos del Enfoque Prioritario'!$B7=2,'Hitos del Enfoque Prioritario'!$F7,"") | R6: =IF('Hitos del Enfoque Prioritario'!$B7=3,'Hitos del Enfoque Prioritario'!$F7,"") | S6: =IF('Hitos del Enfoque Prioritario'!$B7=4,'Hitos del Enfoque Prioritario'!$F7,"") | T6: =IF('Hitos del Enfoque Prioritario'!$B7=5,'Hitos del Enfoque Prioritario'!$F7,"") | U6: =IF('Hitos del Enfoque Prioritario'!$B7=6,'Hitos del Enfoque Prioritario'!$F7,"") | V6: =IF(AND('Hitos del Enfoque Prioritario'!C7='Data Validation'!$A$2,'Hitos del Enfoque Prioritario'!F7=""),"CORRECT",IF('Hitos del Enfoque Prioritario'!C7='Data Validation'!$A$3,"CORRECT",IF('Hitos del Enfoque Prioritario'!B7=1,"ERROR 1",'Data Validation'!$A$4))) -> N/A | W6: =IF(AND('Hitos del Enfoque Prioritario'!C7='Data Validation'!$A$2,'Hitos del Enfoque Prioritario'!F7=""),"CORRECT",IF('Hitos del Enfoque Prioritario'!C7='Data Validation'!$A$3,"CORRECT",IF('Hitos del Enfoque Prioritario'!B7=2,"ERROR 1",'Data Validation'!$A$4))) -> N/A | X6: =IF(AND('Hitos del Enfoque Prioritario'!C7='Data Validation'!$A$2,'Hitos del Enfoque Prioritario'!F7=""),"CORRECT",IF('Hitos del Enfoque Prioritario'!C7='Data Validation'!$A$3,"CORRECT",IF('Hitos del Enfoque Prioritario'!B7=3,"ERROR 1",'Data Validation'!$A$4))) -> N/A | Y6: =IF(AND('Hitos del Enfoque Prioritario'!C7='Data Validation'!$A$2,'Hitos del Enfoque Prioritario'!F7=""),"CORRECT",IF('Hitos del Enfoque Prioritario'!C7='Data Validation'!$A$3,"CORRECT",IF('Hitos del Enfoque Prioritario'!B7=4,"ERROR 1",'Data Validation'!$A$4))) -> N/A | Z6: =IF(AND('Hitos del Enfoque Prioritario'!C7='Data Validation'!$A$2,'Hitos del Enfoque Prioritario'!F7=""),"CORRECT",IF('Hitos del Enfoque Prioritario'!C7='Data Validation'!$A$3,"CORRECT",IF('Hitos del Enfoque Prioritario'!B7=5,"ERROR 1",'Data Validation'!$A$4))) -> N/A | AA6: =IF(AND('Hitos del Enfoque Prioritario'!C7='Data Validation'!$A$2,'Hitos del Enfoque Prioritario'!F7=""),"CORRECT",IF('Hitos del Enfoque Prioritario'!C7='Data Validation'!$A$3,"CORRECT",IF('Hitos del Enfoque Prioritario'!B7=6,"ERROR 1",'Data Validation'!$A$4))) -> N/A | AB6: =IF(AND('Hitos del Enfoque Prioritario'!C7='Data Validation'!$A$3,'Hitos del Enfoque Prioritario'!F7=""),IF('Hitos del Enfoque Prioritario'!B7=1,"ERROR 2",'Data Validation'!$A$4),"CORRECT") -> CORRECT | AC6: =IF(AND('Hitos del Enfoque Prioritario'!C7='Data Validation'!$A$3,'Hitos del Enfoque Prioritario'!F7=""),IF('Hitos del Enfoque Prioritario'!B7=2,"ERROR 2",'Data Validation'!$A$4),"CORRECT") -> CORRECT | AD6: =IF(AND('Hitos del Enfoque Prioritario'!C7='Data Validation'!$A$3,'Hitos del Enfoque Prioritario'!F7=""),IF('Hitos del Enfoque Prioritario'!B7=3,"ERROR 2",'Data Validation'!$A$4),"CORRECT") -> CORRECT | AE6: =IF(AND('Hitos del Enfoque Prioritario'!C7='Data Validation'!$A$3,'Hitos del Enfoque Prioritario'!F7=""),IF('Hitos del Enfoque Prioritario'!B7=4,"ERROR 2",'Data Validation'!$A$4),"CORRECT") -> CORRECT | AF6: =IF(AND('Hitos del Enfoque Prioritario'!C7='Data Validation'!$A$3,'Hitos del Enfoque Prioritario'!F7=""),IF('Hitos del Enfoque Prioritario'!B7=5,"ERROR 2",'Data Validation'!$A$4),"CORRECT") -> CORRECT | AG6: =IF(AND('Hitos del Enfoque Prioritario'!C7='Data Validation'!$A$3,'Hitos del Enfoque Prioritario'!F7=""),IF('Hitos del Enfoque Prioritario'!B7=6,"ERROR 2",'Data Validation'!$A$4),"CORRECT") -> CORRECT
A7: =COUNTIFS('Hitos del Enfoque Prioritario'!B8,"1",'Hitos del Enfoque Prioritario'!C8,'Data Validation'!$A$2) -> 0 | B7: =COUNTIFS('Hitos del Enfoque Prioritario'!B8,"2",'Hitos del Enfoque Prioritario'!C8,'Data Validation'!$A$2) -> 0 | C7: =COUNTIFS('Hitos del Enfoque Prioritario'!B8,"3",'Hitos del Enfoque Prioritario'!C8,'Data Validation'!$A$2) -> 0 | D7: =COUNTIFS('Hitos del Enfoque Prioritario'!B8,"4",'Hitos del Enfoque Prioritario'!C8,'Data Validation'!$A$2) -> 0 | E7: =COUNTIFS('Hitos del Enfoque Prioritario'!B8,"5",'Hitos del Enfoque Prioritario'!C8,'Data Validation'!$A$2) -> 0 | F7: =COUNTIFS('Hitos del Enfoque Prioritario'!B8,"6",'Hitos del Enfoque Prioritario'!C8,'Data Validation'!$A$2) -> 0 | G7: =SUM(A7:F7) -> 0 | H7: =COUNTIFS('Hitos del Enfoque Prioritario'!B8,"1",'Hitos del Enfoque Prioritario'!C8,'Data Validation'!$A$4) -> 0 | I7: =COUNTIFS('Hitos del Enfoque Prioritario'!B8,"2",'Hitos del Enfoque Prioritario'!C8,'Data Validation'!$A$4) -> 0 | J7: =COUNTIFS('Hitos del Enfoque Prioritario'!B8,"3",'Hitos del Enfoque Prioritario'!C8,'Data Validation'!$A$4) -> 0 | K7: =COUNTIFS('Hitos del Enfoque Prioritario'!B8,"4",'Hitos del Enfoque Prioritario'!C8,'Data Validation'!$A$4) -> 0 | L7: =COUNTIFS('Hitos del Enfoque Prioritario'!B8,"5",'Hitos del Enfoque Prioritario'!C8,'Data Validation'!$A$4) -> 0 | M7: =COUNTIFS('Hitos del Enfoque Prioritario'!B8,"6",'Hitos del Enfoque Prioritario'!C8,'Data Validation'!$A$4) -> 0 | N7: =SUM(H7:M7) -> 0 | P7: =IF('Hitos del Enfoque Prioritario'!$B8=1,'Hitos del Enfoque Prioritario'!$F8,"") | Q7: =IF('Hitos del Enfoque Prioritario'!$B8=2,'Hitos del Enfoque Prioritario'!$F8,"") -> 0 | R7: =IF('Hitos del Enfoque Prioritario'!$B8=3,'Hitos del Enfoque Prioritario'!$F8,"") | S7: =IF('Hitos del Enfoque Prioritario'!$B8=4,'Hitos del Enfoque Prioritario'!$F8,"") | T7: =IF('Hitos del Enfoque Prioritario'!$B8=5,'Hitos del Enfoque Prioritario'!$F8,"") | U7: =IF('Hitos del Enfoque Prioritario'!$B8=6,'Hitos del Enfoque Prioritario'!$F8,"") | V7: =IF(AND('Hitos del Enfoque Prioritario'!C8='Data Validation'!$A$2,'Hitos del Enfoque Prioritario'!F8=""),"CORRECT",IF('Hitos del Enfoque Prioritario'!C8='Data Validation'!$A$3,"CORRECT",IF('Hitos del Enfoque Prioritario'!B8=1,"ERROR 1",'Data Validation'!$A$4))) -> N/A | W7: =IF(AND('Hitos del Enfoque Prioritario'!C8='Data Validation'!$A$2,'Hitos del Enfoque Prioritario'!F8=""),"CORRECT",IF('Hitos del Enfoque Prioritario'!C8='Data Validation'!$A$3,"CORRECT",IF('Hitos del Enfoque Prioritario'!B8=2,"ERROR 1",'Data Validation'!$A$4))) -> ERROR 1 | X7: =IF(AND('Hitos del Enfoque Prioritario'!C8='Data Validation'!$A$2,'Hitos del Enfoque Prioritario'!F8=""),"CORRECT",IF('Hitos del Enfoque Prioritario'!C8='Data Validation'!$A$3,"CORRECT",IF('Hitos del Enfoque Prioritario'!B8=3,"ERROR 1",'Data Validation'!$A$4))) -> N/A | Y7: =IF(AND('Hitos del Enfoque Prioritario'!C8='Data Validation'!$A$2,'Hitos del Enfoque Prioritario'!F8=""),"CORRECT",IF('Hitos del Enfoque Prioritario'!C8='Data Validation'!$A$3,"CORRECT",IF('Hitos del Enfoque Prioritario'!B8=4,"ERROR 1",'Data Validation'!$A$4))) -> N/A | Z7: =IF(AND('Hitos del Enfoque Prioritario'!C8='Data Validation'!$A$2,'Hitos del Enfoque Prioritario'!F8=""),"CORRECT",IF('Hitos del Enfoque Prioritario'!C8='Data Validation'!$A$3,"CORRECT",IF('Hitos del Enfoque Prioritario'!B8=5,"ERROR 1",'Data Validation'!$A$4))) -> N/A | AA7: =IF(AND('Hitos del Enfoque Prioritario'!C8='Data Validation'!$A$2,'Hitos del Enfoque Prioritario'!F8=""),"CORRECT",IF('Hitos del Enfoque Prioritario'!C8='Data Validation'!$A$3,"CORRECT",IF('Hitos del Enfoque Prioritario'!B8=6,"ERROR 1",'Data Validation'!$A$4))) -> N/A | AB7: =IF(AND('Hitos del Enfoque Prioritario'!C8='Data Validation'!$A$3,'Hitos del Enfoque Prioritario'!F8=""),IF('Hitos del Enfoque Prioritario'!B8=1,"ERROR 2",'Data Validation'!$A$4),"CORRECT") -> CORRECT | AC7: =IF(AND('Hitos del Enfoque Prioritario'!C8='Data Validation'!$A$3,'Hitos del Enfoque Prioritario'!F8=""),IF('Hitos del Enfoque Prioritario'!B8=2,"ERROR 2",'Data Validation'!$A$4),"CORRECT") -> CORRECT | AD7: =IF(AND('Hitos del Enfoque Prioritario'!C8='Data Validation'!$A$3,'Hitos del Enfoque Prioritario'!F8=""),IF('Hitos del Enfoque Prioritario'!B8=3,"ERROR 2",'Data Validation'!$A$4),"CORRECT") -> CORRECT | AE7: =IF(AND('Hitos del Enfoque Prioritario'!C8='Data Validation'!$A$3,'Hitos del Enfoque Prioritario'!F8=""),IF('Hitos del Enfoque Prioritario'!B8=4,"ERROR 2",'Data Validation'!$A$4),"CORRECT") -> CORRECT | AF7: =IF(AND('Hitos del Enfoque Prioritario'!C8='Data Validation'!$A$3,'Hitos del Enfoque Prioritario'!F8=""),IF('Hitos del Enfoque Prioritario'!B8=5,"ERROR 2",'Data Validation'!$A$4),"CORRECT") -> CORRECT | AG7: =IF(AND('Hitos del Enfoque Prioritario'!C8='Data Validation'!$A$3,'Hitos del Enfoque Prioritario'!F8=""),IF('Hitos del Enfoque Prioritario'!B8=6,"ERROR 2",'Data Validation'!$A$4),"CORRECT") -> CORRECT
A8: =COUNTIFS('Hitos del Enfoque Prioritario'!B9,"1",'Hitos del Enfoque Prioritario'!C9,'Data Validation'!$A$2) -> 0 | B8: =COUNTIFS('Hitos del Enfoque Prioritario'!B9,"2",'Hitos del Enfoque Prioritario'!C9,'Data Validation'!$A$2) -> 0 | C8: =COUNTIFS('Hitos del Enfoque Prioritario'!B9,"3",'Hitos del Enfoque Prioritario'!C9,'Data Validation'!$A$2) -> 0 | D8: =COUNTIFS('Hitos del Enfoque Prioritario'!B9,"4",'Hitos del Enfoque Prioritario'!C9,'Data Validation'!$A$2) -> 0 | E8: =COUNTIFS('Hitos del Enfoque Prioritario'!B9,"5",'Hitos del Enfoque Prioritario'!C9,'Data Validation'!$A$2) -> 0 | F8: =COUNTIFS('Hitos del Enfoque Prioritario'!B9,"6",'Hitos del Enfoque Prioritario'!C9,'Data Validation'!$A$2) -> 0 | G8: =SUM(A8:F8) -> 0 | H8: =COUNTIFS('Hitos del Enfoque Prioritario'!B9,"1",'Hitos del Enfoque Prioritario'!C9,'Data Validation'!$A$4) -> 0 | I8: =COUNTIFS('Hitos del Enfoque Prioritario'!B9,"2",'Hitos del Enfoque Prioritario'!C9,'Data Validation'!$A$4) -> 0 | J8: =COUNTIFS('Hitos del Enfoque Prioritario'!B9,"3",'Hitos del Enfoque Prioritario'!C9,'Data Validation'!$A$4) -> 0 | K8: =COUNTIFS('Hitos del Enfoque Prioritario'!B9,"4",'Hitos del Enfoque Prioritario'!C9,'Data Validation'!$A$4) -> 0 | L8: =COUNTIFS('Hitos del Enfoque Prioritario'!B9,"5",'Hitos del Enfoque Prioritario'!C9,'Data Validation'!$A$4) -> 0 | M8: =COUNTIFS('Hitos del Enfoque Prioritario'!B9,"6",'Hitos del Enfoque Prioritario'!C9,'Data Validation'!$A$4) -> 0 | N8: =SUM(H8:M8) -> 0 | P8: =IF('Hitos del Enfoque Prioritario'!$B9=1,'Hitos del Enfoque Prioritario'!$F9,"") | Q8: =IF('Hitos del Enfoque Prioritario'!$B9=2,'Hitos del Enfoque Prioritario'!$F9,"") | R8: =IF('Hitos del Enfoque Prioritario'!$B9=3,'Hitos del Enfoque Prioritario'!$F9,"") | S8: =IF('Hitos del Enfoque Prioritario'!$B9=4,'Hitos del Enfoque Prioritario'!$F9,"") | T8: =IF('Hitos del Enfoque Prioritario'!$B9=5,'Hitos del Enfoque Prioritario'!$F9,"") | U8: =IF('Hitos del Enfoque Prioritario'!$B9=6,'Hitos del Enfoque Prioritario'!$F9,"") -> 0 | V8: =IF(AND('Hitos del Enfoque Prioritario'!C9='Data Validation'!$A$2,'Hitos del Enfoque Prioritario'!F9=""),"CORRECT",IF('Hitos del Enfoque Prioritario'!C9='Data Validation'!$A$3,"CORRECT",IF('Hitos del Enfoque Prioritario'!B9=1,"ERROR 1",'Data Validation'!$A$4))) -> N/A | W8: =IF(AND('Hitos del Enfoque Prioritario'!C9='Data Validation'!$A$2,'Hitos del Enfoque Prioritario'!F9=""),"CORRECT",IF('Hitos del Enfoque Prioritario'!C9='Data Validation'!$A$3,"CORRECT",IF('Hitos del Enfoque Prioritario'!B9=2,"ERROR 1",'Data Validation'!$A$4))) -> N/A | X8: =IF(AND('Hitos del Enfoque Prioritario'!C9='Data Validation'!$A$2,'Hitos del Enfoque Prioritario'!F9=""),"CORRECT",IF('Hitos del Enfoque Prioritario'!C9='Data Validation'!$A$3,"CORRECT",IF('Hitos del Enfoque Prioritario'!B9=3,"ERROR 1",'Data Validation'!$A$4))) -> N/A | Y8: =IF(AND('Hitos del Enfoque Prioritario'!C9='Data Validation'!$A$2,'Hitos del Enfoque Prioritario'!F9=""),"CORRECT",IF('Hitos del Enfoque Prioritario'!C9='Data Validation'!$A$3,"CORRECT",IF('Hitos del Enfoque Prioritario'!B9=4,"ERROR 1",'Data Validation'!$A$4))) -> N/A | Z8: =IF(AND('Hitos del Enfoque Prioritario'!C9='Data Validation'!$A$2,'Hitos del Enfoque Prioritario'!F9=""),"CORRECT",IF('Hitos del Enfoque Prioritario'!C9='Data Validation'!$A$3,"CORRECT",IF('Hitos del Enfoque Prioritario'!B9=5,"ERROR 1",'Data Validation'!$A$4))) -> N/A | AA8: =IF(AND('Hitos del Enfoque Prioritario'!C9='Data Validation'!$A$2,'Hitos del Enfoque Prioritario'!F9=""),"CORRECT",IF('Hitos del Enfoque Prioritario'!C9='Data Validation'!$A$3,"CORRECT",IF('Hitos del Enfoque Prioritario'!B9=6,"ERROR 1",'Data Validation'!$A$4))) -> ERROR 1 | AB8: =IF(AND('Hitos del Enfoque Prioritario'!C9='Data Validation'!$A$3,'Hitos del Enfoque Prioritario'!F9=""),IF('Hitos del Enfoque Prioritario'!B9=1,"ERROR 2",'Data Validation'!$A$4),"CORRECT") -> CORRECT | AC8: =IF(AND('Hitos del Enfoque Prioritario'!C9='Data Validation'!$A$3,'Hitos del Enfoque Prioritario'!F9=""),IF('Hitos del Enfoque Prioritario'!B9=2,"ERROR 2",'Data Validation'!$A$4),"CORRECT") -> CORRECT | AD8: =IF(AND('Hitos del Enfoque Prioritario'!C9='Data Validation'!$A$3,'Hitos del Enfoque Prioritario'!F9=""),IF('Hitos del Enfoque Prioritario'!B9=3,"ERROR 2",'Data Validation'!$A$4),"CORRECT") -> CORRECT | AE8: =IF(AND('Hitos del Enfoque Prioritario'!C9='Data Validation'!$A$3,'Hitos del Enfoque Prioritario'!F9=""),IF('Hitos del Enfoque Prioritario'!B9=4,"ERROR 2",'Data Validation'!$A$4),"CORRECT") -> CORRECT | AF8: =IF(AND('Hitos del Enfoque Prioritario'!C9='Data Validation'!$A$3,'Hitos del Enfoque Prioritario'!F9=""),IF('Hitos del Enfoque Prioritario'!B9=5,"ERROR 2",'Data Validation'!$A$4),"CORRECT") -> CORRECT | AG8: =IF(AND('Hitos del Enfoque Prioritario'!C9='Data Validation'!$A$3,'Hitos del Enfoque Prioritario'!F9=""),IF('Hitos del Enfoque Prioritario'!B9=6,"ERROR 2",'Data Validation'!$A$4),"CORRECT") -> CORRECT
A9: =COUNTIFS('Hitos del Enfoque Prioritario'!B10,"1",'Hitos del Enfoque Prioritario'!C10,'Data Validation'!$A$2) -> 0 | B9: =COUNTIFS('Hitos del Enfoque Prioritario'!B10,"2",'Hitos del Enfoque Prioritario'!C10,'Data Validation'!$A$2) -> 0 | C9: =COUNTIFS('Hitos del Enfoque Prioritario'!B10,"3",'Hitos del Enfoque Prioritario'!C10,'Data Validation'!$A$2) -> 0 | D9: =COUNTIFS('Hitos del Enfoque Prioritario'!B10,"4",'Hitos del Enfoque Prioritario'!C10,'Data Validation'!$A$2) -> 0 | E9: =COUNTIFS('Hitos del Enfoque Prioritario'!B10,"5",'Hitos del Enfoque Prioritario'!C10,'Data Validation'!$A$2) -> 0 | F9: =COUNTIFS('Hitos del Enfoque Prioritario'!B10,"6",'Hitos del Enfoque Prioritario'!C10,'Data Validation'!$A$2) -> 0 | G9: =SUM(A9:F9) -> 0 | H9: =COUNTIFS('Hitos del Enfoque Prioritario'!B10,"1",'Hitos del Enfoque Prioritario'!C10,'Data Validation'!$A$4) -> 0 | I9: =COUNTIFS('Hitos del Enfoque Prioritario'!B10,"2",'Hitos del Enfoque Prioritario'!C10,'Data Validation'!$A$4) -> 0 | J9: =COUNTIFS('Hitos del Enfoque Prioritario'!B10,"3",'Hitos del Enfoque Prioritario'!C10,'Data Validation'!$A$4) -> 0 | K9: =COUNTIFS('Hitos del Enfoque Prioritario'!B10,"4",'Hitos del Enfoque Prioritario'!C10,'Data Validation'!$A$4) -> 0 | L9: =COUNTIFS('Hitos del Enfoque Prioritario'!B10,"5",'Hitos del Enfoque Prioritario'!C10,'Data Validation'!$A$4) -> 0 | M9: =COUNTIFS('Hitos del Enfoque Prioritario'!B10,"6",'Hitos del Enfoque Prioritario'!C10,'Data Validation'!$A$4) -> 0 | N9: =SUM(H9:M9) -> 0 | P9: =IF('Hitos del Enfoque Prioritario'!$B10=1,'Hitos del Enfoque Prioritario'!$F10,"") -> 0 | Q9: =IF('Hitos del Enfoque Prioritario'!$B10=2,'Hitos del Enfoque Prioritario'!$F10,"") | R9: =IF('Hitos del Enfoque Prioritario'!$B10=3,'Hitos del Enfoque Prioritario'!$F10,"") | S9: =IF('Hitos del Enfoque Prioritario'!$B10=4,'Hitos del Enfoque Prioritario'!$F10,"") | T9: =IF('Hitos del Enfoque Prioritario'!$B10=5,'Hitos del Enfoque Prioritario'!$F10,"") | U9: =IF('Hitos del Enfoque Prioritario'!$B10=6,'Hitos del Enfoque Prioritario'!$F10,"") | V9: =IF(AND('Hitos del Enfoque Prioritario'!C10='Data Validation'!$A$2,'Hitos del Enfoque Prioritario'!F10=""),"CORRECT",IF('Hitos del Enfoque Prioritario'!C10='Data Validation'!$A$3,"CORRECT",IF('Hitos del Enfoque Prioritario'!B10=1,"ERROR 1",'Data Validation'!$A$4))) -> ERROR 1 | W9: =IF(AND('Hitos del Enfoque Prioritario'!C10='Data Validation'!$A$2,'Hitos del Enfoque Prioritario'!F10=""),"CORRECT",IF('Hitos del Enfoque Prioritario'!C10='Data Validation'!$A$3,"CORRECT",IF('Hitos del Enfoque Prioritario'!B10=2,"ERROR 1",'Data Validation'!$A$4))) -> N/A | X9: =IF(AND('Hitos del Enfoque Prioritario'!C10='Data Validation'!$A$2,'Hitos del Enfoque Prioritario'!F10=""),"CORRECT",IF('Hitos del Enfoque Prioritario'!C10='Data Validation'!$A$3,"CORRECT",IF('Hitos del Enfoque Prioritario'!B10=3,"ERROR 1",'Data Validation'!$A$4))) -> N/A | Y9: =IF(AND('Hitos del Enfoque Prioritario'!C10='Data Validation'!$A$2,'Hitos del Enfoque Prioritario'!F10=""),"CORRECT",IF('Hitos del Enfoque Prioritario'!C10='Data Validation'!$A$3,"CORRECT",IF('Hitos del Enfoque Prioritario'!B10=4,"ERROR 1",'Data Validation'!$A$4))) -> N/A | Z9: =IF(AND('Hitos del Enfoque Prioritario'!C10='Data Validation'!$A$2,'Hitos del Enfoque Prioritario'!F10=""),"CORRECT",IF('Hitos del Enfoque Prioritario'!C10='Data Validation'!$A$3,"CORRECT",IF('Hitos del Enfoque Prioritario'!B10=5,"ERROR 1",'Data Validation'!$A$4))) -> N/A | AA9: =IF(AND('Hitos del Enfoque Prioritario'!C10='Data Validation'!$A$2,'Hitos del Enfoque Prioritario'!F10=""),"CORRECT",IF('Hitos del Enfoque Prioritario'!C10='Data Validation'!$A$3,"CORRECT",IF('Hitos del Enfoque Prioritario'!B10=6,"ERROR 1",'Data Validation'!$A$4))) -> N/A | AB9: =IF(AND('Hitos del Enfoque Prioritario'!C10='Data Validation'!$A$3,'Hitos del Enfoque Prioritario'!F10=""),IF('Hitos del Enfoque Prioritario'!B10=1,"ERROR 2",'Data Validation'!$A$4),"CORRECT") -> CORRECT | AC9: =IF(AND('Hitos del Enfoque Prioritario'!C10='Data Validation'!$A$3,'Hitos del Enfoque Prioritario'!F10=""),IF('Hitos del Enfoque Prioritario'!B10=2,"ERROR 2",'Data Validation'!$A$4),"CORRECT") -> CORRECT | AD9: =IF(AND('Hitos del Enfoque Prioritario'!C10='Data Validation'!$A$3,'Hitos del Enfoque Prioritario'!F10=""),IF('Hitos del Enfoque Prioritario'!B10=3,"ERROR 2",'Data Validation'!$A$4),"CORRECT") -> CORRECT | AE9: =IF(AND('Hitos del Enfoque Prioritario'!C10='Data Validation'!$A$3,'Hitos del Enfoque Prioritario'!F10=""),IF('Hitos del Enfoque Prioritario'!B10=4,"ERROR 2",'Data Validation'!$A$4),"CORRECT") -> CORRECT | AF9: =IF(AND('Hitos del Enfoque Prioritario'!C10='Data Validation'!$A$3,'Hitos del Enfoque Prioritario'!F10=""),IF('Hitos del Enfoque Prioritario'!B10=5,"ERROR 2",'Data Validation'!$A$4),"CORRECT") -> CORRECT | AG9: =IF(AND('Hitos del Enfoque Prioritario'!C10='Data Validation'!$A$3,'Hitos del Enfoque Prioritario'!F10=""),IF('Hitos del Enfoque Prioritario'!B10=6,"ERROR 2",'Data Validation'!$A$4),"CORRECT") -> CORRECT
A10: =COUNTIFS('Hitos del Enfoque Prioritario'!B11,"1",'Hitos del Enfoque Prioritario'!C11,'Data Validation'!$A$2) -> 0 | B10: =COUNTIFS('Hitos del Enfoque Prioritario'!B11,"2",'Hitos del Enfoque Prioritario'!C11,'Data Validation'!$A$2) -> 0 | C10: =COUNTIFS('Hitos del Enfoque Prioritario'!B11,"3",'Hitos del Enfoque Prioritario'!C11,'Data Validation'!$A$2) -> 0 | D10: =COUNTIFS('Hitos del Enfoque Prioritario'!B11,"4",'Hitos del Enfoque Prioritario'!C11,'Data Validation'!$A$2) -> 0 | E10: =COUNTIFS('Hitos del Enfoque Prioritario'!B11,"5",'Hitos del Enfoque Prioritario'!C11,'Data Validation'!$A$2) -> 0 | F10: =COUNTIFS('Hitos del Enfoque Prioritario'!B11,"6",'Hitos del Enfoque Prioritario'!C11,'Data Validation'!$A$2) -> 0 | G10: =SUM(A10:F10) -> 0 | H10: =COUNTIFS('Hitos del Enfoque Prioritario'!B11,"1",'Hitos del Enfoque Prioritario'!C11,'Data Validation'!$A$4) -> 0 | I10: =COUNTIFS('Hitos del Enfoque Prioritario'!B11,"2",'Hitos del Enfoque Prioritario'!C11,'Data Validation'!$A$4) -> 0 | J10: =COUNTIFS('Hitos del Enfoque Prioritario'!B11,"3",'Hitos del Enfoque Prioritario'!C11,'Data Validation'!$A$4) -> 0 | K10: =COUNTIFS('Hitos del Enfoque Prioritario'!B11,"4",'Hitos del Enfoque Prioritario'!C11,'Data Validation'!$A$4) -> 0 | L10: =COUNTIFS('Hitos del Enfoque Prioritario'!B11,"5",'Hitos del Enfoque Prioritario'!C11,'Data Validation'!$A$4) -> 0 | M10: =COUNTIFS('Hitos del Enfoque Prioritario'!B11,"6",'Hitos del Enfoque Prioritario'!C11,'Data Validation'!$A$4) -> 0 | N10: =SUM(H10:M10) -> 0 | P10: =IF('Hitos del Enfoque Prioritario'!$B11=1,'Hitos del Enfoque Prioritario'!$F11,"") -> 0 | Q10: =IF('Hitos del Enfoque Prioritario'!$B11=2,'Hitos del Enfoque Prioritario'!$F11,"") | R10: =IF('Hitos del Enfoque Prioritario'!$B11=3,'Hitos del Enfoque Prioritario'!$F11,"") | S10: =IF('Hitos del Enfoque Prioritario'!$B11=4,'Hitos del Enfoque Prioritario'!$F11,"") | T10: =IF('Hitos del Enfoque Prioritario'!$B11=5,'Hitos del Enfoque Prioritario'!$F11,"") | U10: =IF('Hitos del Enfoque Prioritario'!$B11=6,'Hitos del Enfoque Prioritario'!$F11,"") | V10: =IF(AND('Hitos del Enfoque Prioritario'!C11='Data Validation'!$A$2,'Hitos del Enfoque Prioritario'!F11=""),"CORRECT",IF('Hitos del Enfoque Prioritario'!C11='Data Validation'!$A$3,"CORRECT",IF('Hitos del Enfoque Prioritario'!B11=1,"ERROR 1",'Data Validation'!$A$4))) -> ERROR 1 | W10: =IF(AND('Hitos del Enfoque Prioritario'!C11='Data Validation'!$A$2,'Hitos del Enfoque Prioritario'!F11=""),"CORRECT",IF('Hitos del Enfoque Prioritario'!C11='Data Validation'!$A$3,"CORRECT",IF('Hitos del Enfoque Prioritario'!B11=2,"ERROR 1",'Data Validation'!$A$4))) -> N/A | X10: =IF(AND('Hitos del Enfoque Prioritario'!C11='Data Validation'!$A$2,'Hitos del Enfoque Prioritario'!F11=""),"CORRECT",IF('Hitos del Enfoque Prioritario'!C11='Data Validation'!$A$3,"CORRECT",IF('Hitos del Enfoque Prioritario'!B11=3,"ERROR 1",'Data Validation'!$A$4))) -> N/A | Y10: =IF(AND('Hitos del Enfoque Prioritario'!C11='Data Validation'!$A$2,'Hitos del Enfoque Prioritario'!F11=""),"CORRECT",IF('Hitos del Enfoque Prioritario'!C11='Data Validation'!$A$3,"CORRECT",IF('Hitos del Enfoque Prioritario'!B11=4,"ERROR 1",'Data Validation'!$A$4))) -> N/A | Z10: =IF(AND('Hitos del Enfoque Prioritario'!C11='Data Validation'!$A$2,'Hitos del Enfoque Prioritario'!F11=""),"CORRECT",IF('Hitos del Enfoque Prioritario'!C11='Data Validation'!$A$3,"CORRECT",IF('Hitos del Enfoque Prioritario'!B11=5,"ERROR 1",'Data Validation'!$A$4))) -> N/A | AA10: =IF(AND('Hitos del Enfoque Prioritario'!C11='Data Validation'!$A$2,'Hitos del Enfoque Prioritario'!F11=""),"CORRECT",IF('Hitos del Enfoque Prioritario'!C11='Data Validation'!$A$3,"CORRECT",IF('Hitos del Enfoque Prioritario'!B11=6,"ERROR 1",'Data Validation'!$A$4))) -> N/A | AB10: =IF(AND('Hitos del Enfoque Prioritario'!C11='Data Validation'!$A$3,'Hitos del Enfoque Prioritario'!F11=""),IF('Hitos del Enfoque Prioritario'!B11=1,"ERROR 2",'Data Validation'!$A$4),"CORRECT") -> CORRECT | AC10: =IF(AND('Hitos del Enfoque Prioritario'!C11='Data Validation'!$A$3,'Hitos del Enfoque Prioritario'!F11=""),IF('Hitos del Enfoque Prioritario'!B11=2,"ERROR 2",'Data Validation'!$A$4),"CORRECT") -> CORRECT | AD10: =IF(AND('Hitos del Enfoque Prioritario'!C11='Data Validation'!$A$3,'Hitos del Enfoque Prioritario'!F11=""),IF('Hitos del Enfoque Prioritario'!B11=3,"ERROR 2",'Data Validation'!$A$4),"CORRECT") -> CORRECT | AE10: =IF(AND('Hitos del Enfoque Prioritario'!C11='Data Validation'!$A$3,'Hitos del Enfoque Prioritario'!F11=""),IF('Hitos del Enfoque Prioritario'!B11=4,"ERROR 2",'Data Validation'!$A$4),"CORRECT") -> CORRECT | AF10: =IF(AND('Hitos del Enfoque Prioritario'!C11='Data Validation'!$A$3,'Hitos del Enfoque Prioritario'!F11=""),IF('Hitos del Enfoque Prioritario'!B11=5,"ERROR 2",'Data Validation'!$A$4),"CORRECT") -> CORRECT | AG10: =IF(AND('Hitos del Enfoque Prioritario'!C11='Data Validation'!$A$3,'Hitos del Enfoque Prioritario'!F11=""),IF('Hitos del Enfoque Prioritario'!B11=6,"ERROR 2",'Data Validation'!$A$4),"CORRECT") -> CORRECT
A11: =COUNTIFS('Hitos del Enfoque Prioritario'!B12,"1",'Hitos del Enfoque Prioritario'!C12,'Data Validation'!$A$2) -> 0 | B11: =COUNTIFS('Hitos del Enfoque Prioritario'!B12,"2",'Hitos del Enfoque Prioritario'!C12,'Data Validation'!$A$2) -> 0 | C11: =COUNTIFS('Hitos del Enfoque Prioritario'!B12,"3",'Hitos del Enfoque Prioritario'!C12,'Data Validation'!$A$2) -> 0 | D11: =COUNTIFS('Hitos del Enfoque Prioritario'!B12,"4",'Hitos del Enfoque Prioritario'!C12,'Data Validation'!$A$2) -> 0 | E11: =COUNTIFS('Hitos del Enfoque Prioritario'!B12,"5",'Hitos del Enfoque Prioritario'!C12,'Data Validation'!$A$2) -> 0 | F11: =COUNTIFS('Hitos del Enfoque Prioritario'!B12,"6",'Hitos del Enfoque Prioritario'!C12,'Data Validation'!$A$2) -> 0 | G11: =SUM(A11:F11) -> 0 | H11: =COUNTIFS('Hitos del Enfoque Prioritario'!B12,"1",'Hitos del Enfoque Prioritario'!C12,'Data Validation'!$A$4) -> 0 | I11: =COUNTIFS('Hitos del Enfoque Prioritario'!B12,"2",'Hitos del Enfoque Prioritario'!C12,'Data Validation'!$A$4) -> 0 | J11: =COUNTIFS('Hitos del Enfoque Prioritario'!B12,"3",'Hitos del Enfoque Prioritario'!C12,'Data Validation'!$A$4) -> 0 | K11: =COUNTIFS('Hitos del Enfoque Prioritario'!B12,"4",'Hitos del Enfoque Prioritario'!C12,'Data Validation'!$A$4) -> 0 | L11: =COUNTIFS('Hitos del Enfoque Prioritario'!B12,"5",'Hitos del Enfoque Prioritario'!C12,'Data Validation'!$A$4) -> 0 | M11: =COUNTIFS('Hitos del Enfoque Prioritario'!B12,"6",'Hitos del Enfoque Prioritario'!C12,'Data Validation'!$A$4) -> 0 | N11: =SUM(H11:M11) -> 0 | P11: =IF('Hitos del Enfoque Prioritario'!$B12=1,'Hitos del Enfoque Prioritario'!$F12,"") | Q11: =IF('Hitos del Enfoque Prioritario'!$B12=2,'Hitos del Enfoque Prioritario'!$F12,"") -> 0 | R11: =IF('Hitos del Enfoque Prioritario'!$B12=3,'Hitos del Enfoque Prioritario'!$F12,"") | S11: =IF('Hitos del Enfoque Prioritario'!$B12=4,'Hitos del Enfoque Prioritario'!$F12,"") | T11: =IF('Hitos del Enfoque Prioritario'!$B12=5,'Hitos del Enfoque Prioritario'!$F12,"") | U11: =IF('Hitos del Enfoque Prioritario'!$B12=6,'Hitos del Enfoque Prioritario'!$F12,"") | V11: =IF(AND('Hitos del Enfoque Prioritario'!C12='Data Validation'!$A$2,'Hitos del Enfoque Prioritario'!F12=""),"CORRECT",IF('Hitos del Enfoque Prioritario'!C12='Data Validation'!$A$3,"CORRECT",IF('Hitos del Enfoque Prioritario'!B12=1,"ERROR 1",'Data Validation'!$A$4))) -> N/A | W11: =IF(AND('Hitos del Enfoque Prioritario'!C12='Data Validation'!$A$2,'Hitos del Enfoque Prioritario'!F12=""),"CORRECT",IF('Hitos del Enfoque Prioritario'!C12='Data Validation'!$A$3,"CORRECT",IF('Hitos del Enfoque Prioritario'!B12=2,"ERROR 1",'Data Validation'!$A$4))) -> ERROR 1 | X11: =IF(AND('Hitos del Enfoque Prioritario'!C12='Data Validation'!$A$2,'Hitos del Enfoque Prioritario'!F12=""),"CORRECT",IF('Hitos del Enfoque Prioritario'!C12='Data Validation'!$A$3,"CORRECT",IF('Hitos del Enfoque Prioritario'!B12=3,"ERROR 1",'Data Validation'!$A$4))) -> N/A | Y11: =IF(AND('Hitos del Enfoque Prioritario'!C12='Data Validation'!$A$2,'Hitos del Enfoque Prioritario'!F12=""),"CORRECT",IF('Hitos del Enfoque Prioritario'!C12='Data Validation'!$A$3,"CORRECT",IF('Hitos del Enfoque Prioritario'!B12=4,"ERROR 1",'Data Validation'!$A$4))) -> N/A | Z11: =IF(AND('Hitos del Enfoque Prioritario'!C12='Data Validation'!$A$2,'Hitos del Enfoque Prioritario'!F12=""),"CORRECT",IF('Hitos del Enfoque Prioritario'!C12='Data Validation'!$A$3,"CORRECT",IF('Hitos del Enfoque Prioritario'!B12=5,"ERROR 1",'Data Validation'!$A$4))) -> N/A | AA11: =IF(AND('Hitos del Enfoque Prioritario'!C12='Data Validation'!$A$2,'Hitos del Enfoque Prioritario'!F12=""),"CORRECT",IF('Hitos del Enfoque Prioritario'!C12='Data Validation'!$A$3,"CORRECT",IF('Hitos del Enfoque Prioritario'!B12=6,"ERROR 1",'Data Validation'!$A$4))) -> N/A | AB11: =IF(AND('Hitos del Enfoque Prioritario'!C12='Data Validation'!$A$3,'Hitos del Enfoque Prioritario'!F12=""),IF('Hitos del Enfoque Prioritario'!B12=1,"ERROR 2",'Data Validation'!$A$4),"CORRECT") -> CORRECT | AC11: =IF(AND('Hitos del Enfoque Prioritario'!C12='Data Validation'!$A$3,'Hitos del Enfoque Prioritario'!F12=""),IF('Hitos del Enfoque Prioritario'!B12=2,"ERROR 2",'Data Validation'!$A$4),"CORRECT") -> CORRECT | AD11: =IF(AND('Hitos del Enfoque Prioritario'!C12='Data Validation'!$A$3,'Hitos del Enfoque Prioritario'!F12=""),IF('Hitos del Enfoque Prioritario'!B12=3,"ERROR 2",'Data Validation'!$A$4),"CORRECT") -> CORRECT | AE11: =IF(AND('Hitos del Enfoque Prioritario'!C12='Data Validation'!$A$3,'Hitos del Enfoque Prioritario'!F12=""),IF('Hitos del Enfoque Prioritario'!B12=4,"ERROR 2",'Data Validation'!$A$4),"CORRECT") -> CORRECT | AF11: =IF(AND('Hitos del Enfoque Prioritario'!C12='Data Validation'!$A$3,'Hitos del Enfoque Prioritario'!F12=""),IF('Hitos del Enfoque Prioritario'!B12=5,"ERROR 2",'Data Validation'!$A$4),"CORRECT") -> CORRECT | AG11: =IF(AND('Hitos del Enfoque Prioritario'!C12='Data Validation'!$A$3,'Hitos del Enfoque Prioritario'!F12=""),IF('Hitos del Enfoque Prioritario'!B12=6,"ERROR 2",'Data Validation'!$A$4),"CORRECT") -> CORRECT
A12: =COUNTIFS('Hitos del Enfoque Prioritario'!B13,"1",'Hitos del Enfoque Prioritario'!C13,'Data Validation'!$A$2) -> 0 | B12: =COUNTIFS('Hitos del Enfoque Prioritario'!B13,"2",'Hitos del Enfoque Prioritario'!C13,'Data Validation'!$A$2) -> 0 | C12: =COUNTIFS('Hitos del Enfoque Prioritario'!B13,"3",'Hitos del Enfoque Prioritario'!C13,'Data Validation'!$A$2) -> 0 | D12: =COUNTIFS('Hitos del Enfoque Prioritario'!B13,"4",'Hitos del Enfoque Prioritario'!C13,'Data Validation'!$A$2) -> 0 | E12: =COUNTIFS('Hitos del Enfoque Prioritario'!B13,"5",'Hitos del Enfoque Prioritario'!C13,'Data Validation'!$A$2) -> 0 | F12: =COUNTIFS('Hitos del Enfoque Prioritario'!B13,"6",'Hitos del Enfoque Prioritario'!C13,'Data Validation'!$A$2) -> 0 | G12: =SUM(A12:F12) -> 0 | H12: =COUNTIFS('Hitos del Enfoque Prioritario'!B13,"1",'Hitos del Enfoque Prioritario'!C13,'Data Validation'!$A$4) -> 0 | I12: =COUNTIFS('Hitos del Enfoque Prioritario'!B13,"2",'Hitos del Enfoque Prioritario'!C13,'Data Validation'!$A$4) -> 0 | J12: =COUNTIFS('Hitos del Enfoque Prioritario'!B13,"3",'Hitos del Enfoque Prioritario'!C13,'Data Validation'!$A$4) -> 0 | K12: =COUNTIFS('Hitos del Enfoque Prioritario'!B13,"4",'Hitos del Enfoque Prioritario'!C13,'Data Validation'!$A$4) -> 0 | L12: =COUNTIFS('Hitos del Enfoque Prioritario'!B13,"5",'Hitos del Enfoque Prioritario'!C13,'Data Validation'!$A$4) -> 0 | M12: =COUNTIFS('Hitos del Enfoque Prioritario'!B13,"6",'Hitos del Enfoque Prioritario'!C13,'Data Validation'!$A$4) -> 0 | N12: =SUM(H12:M12) -> 0 | P12: =IF('Hitos del Enfoque Prioritario'!$B13=1,'Hitos del Enfoque Prioritario'!$F13,"") | Q12: =IF('Hitos del Enfoque Prioritario'!$B13=2,'Hitos del Enfoque Prioritario'!$F13,"") -> 0 | R12: =IF('Hitos del Enfoque Prioritario'!$B13=3,'Hitos del Enfoque Prioritario'!$F13,"") | S12: =IF('Hitos del Enfoque Prioritario'!$B13=4,'Hitos del Enfoque Prioritario'!$F13,"") | T12: =IF('Hitos del Enfoque Prioritario'!$B13=5,'Hitos del Enfoque Prioritario'!$F13,"") | U12: =IF('Hitos del Enfoque Prioritario'!$B13=6,'Hitos del Enfoque Prioritario'!$F13,"") | V12: =IF(AND('Hitos del Enfoque Prioritario'!C13='Data Validation'!$A$2,'Hitos del Enfoque Prioritario'!F13=""),"CORRECT",IF('Hitos del Enfoque Prioritario'!C13='Data Validation'!$A$3,"CORRECT",IF('Hitos del Enfoque Prioritario'!B13=1,"ERROR 1",'Data Validation'!$A$4))) -> N/A | W12: =IF(AND('Hitos del Enfoque Prioritario'!C13='Data Validation'!$A$2,'Hitos del Enfoque Prioritario'!F13=""),"CORRECT",IF('Hitos del Enfoque Prioritario'!C13='Data Validation'!$A$3,"CORRECT",IF('Hitos del Enfoque Prioritario'!B13=2,"ERROR 1",'Data Validation'!$A$4))) -> ERROR 1 | X12: =IF(AND('Hitos del Enfoque Prioritario'!C13='Data Validation'!$A$2,'Hitos del Enfoque Prioritario'!F13=""),"CORRECT",IF('Hitos del Enfoque Prioritario'!C13='Data Validation'!$A$3,"CORRECT",IF('Hitos del Enfoque Prioritario'!B13=3,"ERROR 1",'Data Validation'!$A$4))) -> N/A | Y12: =IF(AND('Hitos del Enfoque Prioritario'!C13='Data Validation'!$A$2,'Hitos del Enfoque Prioritario'!F13=""),"CORRECT",IF('Hitos del Enfoque Prioritario'!C13='Data Validation'!$A$3,"CORRECT",IF('Hitos del Enfoque Prioritario'!B13=4,"ERROR 1",'Data Validation'!$A$4))) -> N/A | Z12: =IF(AND('Hitos del Enfoque Prioritario'!C13='Data Validation'!$A$2,'Hitos del Enfoque Prioritario'!F13=""),"CORRECT",IF('Hitos del Enfoque Prioritario'!C13='Data Validation'!$A$3,"CORRECT",IF('Hitos del Enfoque Prioritario'!B13=5,"ERROR 1",'Data Validation'!$A$4))) -> N/A | AA12: =IF(AND('Hitos del Enfoque Prioritario'!C13='Data Validation'!$A$2,'Hitos del Enfoque Prioritario'!F13=""),"CORRECT",IF('Hitos del Enfoque Prioritario'!C13='Data Validation'!$A$3,"CORRECT",IF('Hitos del Enfoque Prioritario'!B13=6,"ERROR 1",'Data Validation'!$A$4))) -> N/A | AB12: =IF(AND('Hitos del Enfoque Prioritario'!C13='Data Validation'!$A$3,'Hitos del Enfoque Prioritario'!F13=""),IF('Hitos del Enfoque Prioritario'!B13=1,"ERROR 2",'Data Validation'!$A$4),"CORRECT") -> CORRECT | AC12: =IF(AND('Hitos del Enfoque Prioritario'!C13='Data Validation'!$A$3,'Hitos del Enfoque Prioritario'!F13=""),IF('Hitos del Enfoque Prioritario'!B13=2,"ERROR 2",'Data Validation'!$A$4),"CORRECT") -> CORRECT | AD12: =IF(AND('Hitos del Enfoque Prioritario'!C13='Data Validation'!$A$3,'Hitos del Enfoque Prioritario'!F13=""),IF('Hitos del Enfoque Prioritario'!B13=3,"ERROR 2",'Data Validation'!$A$4),"CORRECT") -> CORRECT | AE12: =IF(AND('Hitos del Enfoque Prioritario'!C13='Data Validation'!$A$3,'Hitos del Enfoque Prioritario'!F13=""),IF('Hitos del Enfoque Prioritario'!B13=4,"ERROR 2",'Data Validation'!$A$4),"CORRECT") -> CORRECT | AF12: =IF(AND('Hitos del Enfoque Prioritario'!C13='Data Validation'!$A$3,'Hitos del Enfoque Prioritario'!F13=""),IF('Hitos del Enfoque Prioritario'!B13=5,"ERROR 2",'Data Validation'!$A$4),"CORRECT") -> CORRECT | AG12: =IF(AND('Hitos del Enfoque Prioritario'!C13='Data Validation'!$A$3,'Hitos del Enfoque Prioritario'!F13=""),IF('Hitos del Enfoque Prioritario'!B13=6,"ERROR 2",'Data Validation'!$A$4),"CORRECT") -> CORRECT
A13: =COUNTIFS('Hitos del Enfoque Prioritario'!B14,"1",'Hitos del Enfoque Prioritario'!C14,'Data Validation'!$A$2) -> 0 | B13: =COUNTIFS('Hitos del Enfoque Prioritario'!B14,"2",'Hitos del Enfoque Prioritario'!C14,'Data Validation'!$A$2) -> 0 | C13: =COUNTIFS('Hitos del Enfoque Prioritario'!B14,"3",'Hitos del Enfoque Prioritario'!C14,'Data Validation'!$A$2) -> 0 | D13: =COUNTIFS('Hitos del Enfoque Prioritario'!B14,"4",'Hitos del Enfoque Prioritario'!C14,'Data Validation'!$A$2) -> 0 | E13: =COUNTIFS('Hitos del Enfoque Prioritario'!B14,"5",'Hitos del Enfoque Prioritario'!C14,'Data Validation'!$A$2) -> 0 | F13: =COUNTIFS('Hitos del Enfoque Prioritario'!B14,"6",'Hitos del Enfoque Prioritario'!C14,'Data Validation'!$A$2) -> 0 | G13: =SUM(A13:F13) -> 0 | H13: =COUNTIFS('Hitos del Enfoque Prioritario'!B14,"1",'Hitos del Enfoque Prioritario'!C14,'Data Validation'!$A$4) -> 0 | I13: =COUNTIFS('Hitos del Enfoque Prioritario'!B14,"2",'Hitos del Enfoque Prioritario'!C14,'Data Validation'!$A$4) -> 0 | J13: =COUNTIFS('Hitos del Enfoque Prioritario'!B14,"3",'Hitos del Enfoque Prioritario'!C14,'Data Validation'!$A$4) -> 0 | K13: =COUNTIFS('Hitos del Enfoque Prioritario'!B14,"4",'Hitos del Enfoque Prioritario'!C14,'Data Validation'!$A$4) -> 0 | L13: =COUNTIFS('Hitos del Enfoque Prioritario'!B14,"5",'Hitos del Enfoque Prioritario'!C14,'Data Validation'!$A$4) -> 0 | M13: =COUNTIFS('Hitos del Enfoque Prioritario'!B14,"6",'Hitos del Enfoque Prioritario'!C14,'Data Validation'!$A$4) -> 0 | N13: =SUM(H13:M13) -> 0 | P13: =IF('Hitos del Enfoque Prioritario'!$B14=1,'Hitos del Enfoque Prioritario'!$F14,"") | Q13: =IF('Hitos del Enfoque Prioritario'!$B14=2,'Hitos del Enfoque Prioritario'!$F14,"") | R13: =IF('Hitos del Enfoque Prioritario'!$B14=3,'Hitos del Enfoque Prioritario'!$F14,"") | S13: =IF('Hitos del Enfoque Prioritario'!$B14=4,'Hitos del Enfoque Prioritario'!$F14,"") | T13: =IF('Hitos del Enfoque Prioritario'!$B14=5,'Hitos del Enfoque Prioritario'!$F14,"") | U13: =IF('Hitos del Enfoque Prioritario'!$B14=6,'Hitos del Enfoque Prioritario'!$F14,"") -> 0 | V13: =IF(AND('Hitos del Enfoque Prioritario'!C14='Data Validation'!$A$2,'Hitos del Enfoque Prioritario'!F14=""),"CORRECT",IF('Hitos del Enfoque Prioritario'!C14='Data Validation'!$A$3,"CORRECT",IF('Hitos del Enfoque Prioritario'!B14=1,"ERROR 1",'Data Validation'!$A$4))) -> N/A | W13: =IF(AND('Hitos del Enfoque Prioritario'!C14='Data Validation'!$A$2,'Hitos del Enfoque Prioritario'!F14=""),"CORRECT",IF('Hitos del Enfoque Prioritario'!C14='Data Validation'!$A$3,"CORRECT",IF('Hitos del Enfoque Prioritario'!B14=2,"ERROR 1",'Data Validation'!$A$4))) -> N/A | X13: =IF(AND('Hitos del Enfoque Prioritario'!C14='Data Validation'!$A$2,'Hitos del Enfoque Prioritario'!F14=""),"CORRECT",IF('Hitos del Enfoque Prioritario'!C14='Data Validation'!$A$3,"CORRECT",IF('Hitos del Enfoque Prioritario'!B14=3,"ERROR 1",'Data Validation'!$A$4))) -> N/A | Y13: =IF(AND('Hitos del Enfoque Prioritario'!C14='Data Validation'!$A$2,'Hitos del Enfoque Prioritario'!F14=""),"CORRECT",IF('Hitos del Enfoque Prioritario'!C14='Data Validation'!$A$3,"CORRECT",IF('Hitos del Enfoque Prioritario'!B14=4,"ERROR 1",'Data Validation'!$A$4))) -> N/A | Z13: =IF(AND('Hitos del Enfoque Prioritario'!C14='Data Validation'!$A$2,'Hitos del Enfoque Prioritario'!F14=""),"CORRECT",IF('Hitos del Enfoque Prioritario'!C14='Data Validation'!$A$3,"CORRECT",IF('Hitos del Enfoque Prioritario'!B14=5,"ERROR 1",'Data Validation'!$A$4))) -> N/A | AA13: =IF(AND('Hitos del Enfoque Prioritario'!C14='Data Validation'!$A$2,'Hitos del Enfoque Prioritario'!F14=""),"CORRECT",IF('Hitos del Enfoque Prioritario'!C14='Data Validation'!$A$3,"CORRECT",IF('Hitos del Enfoque Prioritario'!B14=6,"ERROR 1",'Data Validation'!$A$4))) -> ERROR 1 | AB13: =IF(AND('Hitos del Enfoque Prioritario'!C14='Data Validation'!$A$3,'Hitos del Enfoque Prioritario'!F14=""),IF('Hitos del Enfoque Prioritario'!B14=1,"ERROR 2",'Data Validation'!$A$4),"CORRECT") -> CORRECT | AC13: =IF(AND('Hitos del Enfoque Prioritario'!C14='Data Validation'!$A$3,'Hitos del Enfoque Prioritario'!F14=""),IF('Hitos del Enfoque Prioritario'!B14=2,"ERROR 2",'Data Validation'!$A$4),"CORRECT") -> CORRECT | AD13: =IF(AND('Hitos del Enfoque Prioritario'!C14='Data Validation'!$A$3,'Hitos del Enfoque Prioritario'!F14=""),IF('Hitos del Enfoque Prioritario'!B14=3,"ERROR 2",'Data Validation'!$A$4),"CORRECT") -> CORRECT | AE13: =IF(AND('Hitos del Enfoque Prioritario'!C14='Data Validation'!$A$3,'Hitos del Enfoque Prioritario'!F14=""),IF('Hitos del Enfoque Prioritario'!B14=4,"ERROR 2",'Data Validation'!$A$4),"CORRECT") -> CORRECT | AF13: =IF(AND('Hitos del Enfoque Prioritario'!C14='Data Validation'!$A$3,'Hitos del Enfoque Prioritario'!F14=""),IF('Hitos del Enfoque Prioritario'!B14=5,"ERROR 2",'Data Validation'!$A$4),"CORRECT") -> CORRECT | AG13: =IF(AND('Hitos del Enfoque Prioritario'!C14='Data Validation'!$A$3,'Hitos del Enfoque Prioritario'!F14=""),IF('Hitos del Enfoque Prioritario'!B14=6,"ERROR 2",'Data Validation'!$A$4),"CORRECT") -> CORRECT
A14: =COUNTIFS('Hitos del Enfoque Prioritario'!B15,"1",'Hitos del Enfoque Prioritario'!C15,'Data Validation'!$A$2) -> 0 | B14: =COUNTIFS('Hitos del Enfoque Prioritario'!B15,"2",'Hitos del Enfoque Prioritario'!C15,'Data Validation'!$A$2) -> 0 | C14: =COUNTIFS('Hitos del Enfoque Prioritario'!B15,"3",'Hitos del Enfoque Prioritario'!C15,'Data Validation'!$A$2) -> 0 | D14: =COUNTIFS('Hitos del Enfoque Prioritario'!B15,"4",'Hitos del Enfoque Prioritario'!C15,'Data Validation'!$A$2) -> 0 | E14: =COUNTIFS('Hitos del Enfoque Prioritario'!B15,"5",'Hitos del Enfoque Prioritario'!C15,'Data Validation'!$A$2) -> 0 | F14: =COUNTIFS('Hitos del Enfoque Prioritario'!B15,"6",'Hitos del Enfoque Prioritario'!C15,'Data Validation'!$A$2) -> 0 | G14: =SUM(A14:F14) -> 0 | H14: =COUNTIFS('Hitos del Enfoque Prioritario'!B15,"1",'Hitos del Enfoque Prioritario'!C15,'Data Validation'!$A$4) -> 0 | I14: =COUNTIFS('Hitos del Enfoque Prioritario'!B15,"2",'Hitos del Enfoque Prioritario'!C15,'Data Validation'!$A$4) -> 0 | J14: =COUNTIFS('Hitos del Enfoque Prioritario'!B15,"3",'Hitos del Enfoque Prioritario'!C15,'Data Validation'!$A$4) -> 0 | K14: =COUNTIFS('Hitos del Enfoque Prioritario'!B15,"4",'Hitos del Enfoque Prioritario'!C15,'Data Validation'!$A$4) -> 0 | L14: =COUNTIFS('Hitos del Enfoque Prioritario'!B15,"5",'Hitos del Enfoque Prioritario'!C15,'Data Validation'!$A$4) -> 0 | M14: =COUNTIFS('Hitos del Enfoque Prioritario'!B15,"6",'Hitos del Enfoque Prioritario'!C15,'Data Validation'!$A$4) -> 0 | N14: =SUM(H14:M14) -> 0 | P14: =IF('Hitos del Enfoque Prioritario'!$B15=1,'Hitos del Enfoque Prioritario'!$F15,"") | Q14: =IF('Hitos del Enfoque Prioritario'!$B15=2,'Hitos del Enfoque Prioritario'!$F15,"") -> 0 | R14: =IF('Hitos del Enfoque Prioritario'!$B15=3,'Hitos del Enfoque Prioritario'!$F15,"") | S14: =IF('Hitos del Enfoque Prioritario'!$B15=4,'Hitos del Enfoque Prioritario'!$F15,"") | T14: =IF('Hitos del Enfoque Prioritario'!$B15=5,'Hitos del Enfoque Prioritario'!$F15,"") | U14: =IF('Hitos del Enfoque Prioritario'!$B15=6,'Hitos del Enfoque Prioritario'!$F15,"") | V14: =IF(AND('Hitos del Enfoque Prioritario'!C15='Data Validation'!$A$2,'Hitos del Enfoque Prioritario'!F15=""),"CORRECT",IF('Hitos del Enfoque Prioritario'!C15='Data Validation'!$A$3,"CORRECT",IF('Hitos del Enfoque Prioritario'!B15=1,"ERROR 1",'Data Validation'!$A$4))) -> N/A | W14: =IF(AND('Hitos del Enfoque Prioritario'!C15='Data Validation'!$A$2,'Hitos del Enfoque Prioritario'!F15=""),"CORRECT",IF('Hitos del Enfoque Prioritario'!C15='Data Validation'!$A$3,"CORRECT",IF('Hitos del Enfoque Prioritario'!B15=2,"ERROR 1",'Data Validation'!$A$4))) -> ERROR 1 | X14: =IF(AND('Hitos del Enfoque Prioritario'!C15='Data Validation'!$A$2,'Hitos del Enfoque Prioritario'!F15=""),"CORRECT",IF('Hitos del Enfoque Prioritario'!C15='Data Validation'!$A$3,"CORRECT",IF('Hitos del Enfoque Prioritario'!B15=3,"ERROR 1",'Data Validation'!$A$4))) -> N/A | Y14: =IF(AND('Hitos del Enfoque Prioritario'!C15='Data Validation'!$A$2,'Hitos del Enfoque Prioritario'!F15=""),"CORRECT",IF('Hitos del Enfoque Prioritario'!C15='Data Validation'!$A$3,"CORRECT",IF('Hitos del Enfoque Prioritario'!B15=4,"ERROR 1",'Data Validation'!$A$4))) -> N/A | Z14: =IF(AND('Hitos del Enfoque Prioritario'!C15='Data Validation'!$A$2,'Hitos del Enfoque Prioritario'!F15=""),"CORRECT",IF('Hitos del Enfoque Prioritario'!C15='Data Validation'!$A$3,"CORRECT",IF('Hitos del Enfoque Prioritario'!B15=5,"ERROR 1",'Data Validation'!$A$4))) -> N/A | AA14: =IF(AND('Hitos del Enfoque Prioritario'!C15='Data Validation'!$A$2,'Hitos del Enfoque Prioritario'!F15=""),"CORRECT",IF('Hitos del Enfoque Prioritario'!C15='Data Validation'!$A$3,"CORRECT",IF('Hitos del Enfoque Prioritario'!B15=6,"ERROR 1",'Data Validation'!$A$4))) -> N/A | AB14: =IF(AND('Hitos del Enfoque Prioritario'!C15='Data Validation'!$A$3,'Hitos del Enfoque Prioritario'!F15=""),IF('Hitos del Enfoque Prioritario'!B15=1,"ERROR 2",'Data Validation'!$A$4),"CORRECT") -> CORRECT | AC14: =IF(AND('Hitos del Enfoque Prioritario'!C15='Data Validation'!$A$3,'Hitos del Enfoque Prioritario'!F15=""),IF('Hitos del Enfoque Prioritario'!B15=2,"ERROR 2",'Data Validation'!$A$4),"CORRECT") -> CORRECT | AD14: =IF(AND('Hitos del Enfoque Prioritario'!C15='Data Validation'!$A$3,'Hitos del Enfoque Prioritario'!F15=""),IF('Hitos del Enfoque Prioritario'!B15=3,"ERROR 2",'Data Validation'!$A$4),"CORRECT") -> CORRECT | AE14: =IF(AND('Hitos del Enfoque Prioritario'!C15='Data Validation'!$A$3,'Hitos del Enfoque Prioritario'!F15=""),IF('Hitos del Enfoque Prioritario'!B15=4,"ERROR 2",'Data Validation'!$A$4),"CORRECT") -> CORRECT | AF14: =IF(AND('Hitos del Enfoque Prioritario'!C15='Data Validation'!$A$3,'Hitos del Enfoque Prioritario'!F15=""),IF('Hitos del Enfoque Prioritario'!B15=5,"ERROR 2",'Data Validation'!$A$4),"CORRECT") -> CORRECT | AG14: =IF(AND('Hitos del Enfoque Prioritario'!C15='Data Validation'!$A$3,'Hitos del Enfoque Prioritario'!F15=""),IF('Hitos del Enfoque Prioritario'!B15=6,"ERROR 2",'Data Validation'!$A$4),"CORRECT") -> CORRECT
A15: =COUNTIFS('Hitos del Enfoque Prioritario'!B16,"1",'Hitos del Enfoque Prioritario'!C16,'Data Validation'!$A$2) -> 0 | B15: =COUNTIFS('Hitos del Enfoque Prioritario'!B16,"2",'Hitos del Enfoque Prioritario'!C16,'Data Validation'!$A$2) -> 0 | C15: =COUNTIFS('Hitos del Enfoque Prioritario'!B16,"3",'Hitos del Enfoque Prioritario'!C16,'Data Validation'!$A$2) -> 0 | D15: =COUNTIFS('Hitos del Enfoque Prioritario'!B16,"4",'Hitos del Enfoque Prioritario'!C16,'Data Validation'!$A$2) -> 0 | E15: =COUNTIFS('Hitos del Enfoque Prioritario'!B16,"5",'Hitos del Enfoque Prioritario'!C16,'Data Validation'!$A$2) -> 0 | F15: =COUNTIFS('Hitos del Enfoque Prioritario'!B16,"6",'Hitos del Enfoque Prioritario'!C16,'Data Validation'!$A$2) -> 0 | G15: =SUM(A15:F15) -> 0 | H15: =COUNTIFS('Hitos del Enfoque Prioritario'!B16,"1",'Hitos del Enfoque Prioritario'!C16,'Data Validation'!$A$4) -> 0 | I15: =COUNTIFS('Hitos del Enfoque Prioritario'!B16,"2",'Hitos del Enfoque Prioritario'!C16,'Data Validation'!$A$4) -> 0 | J15: =COUNTIFS('Hitos del Enfoque Prioritario'!B16,"3",'Hitos del Enfoque Prioritario'!C16,'Data Validation'!$A$4) -> 0 | K15: =COUNTIFS('Hitos del Enfoque Prioritario'!B16,"4",'Hitos del Enfoque Prioritario'!C16,'Data Validation'!$A$4) -> 0 | L15: =COUNTIFS('Hitos del Enfoque Prioritario'!B16,"5",'Hitos del Enfoque Prioritario'!C16,'Data Validation'!$A$4) -> 0 | M15: =COUNTIFS('Hitos del Enfoque Prioritario'!B16,"6",'Hitos del Enfoque Prioritario'!C16,'Data Validation'!$A$4) -> 0 | N15: =SUM(H15:M15) -> 0 | P15: =IF('Hitos del Enfoque Prioritario'!$B16=1,'Hitos del Enfoque Prioritario'!$F16,"") | Q15: =IF('Hitos del Enfoque Prioritario'!$B16=2,'Hitos del Enfoque Prioritario'!$F16,"") | R15: =IF('Hitos del Enfoque Prioritario'!$B16=3,'Hitos del Enfoque Prioritario'!$F16,"") | S15: =IF('Hitos del Enfoque Prioritario'!$B16=4,'Hitos del Enfoque Prioritario'!$F16,"") | T15: =IF('Hitos del Enfoque Prioritario'!$B16=5,'Hitos del Enfoque Prioritario'!$F16,"") | U15: =IF('Hitos del Enfoque Prioritario'!$B16=6,'Hitos del Enfoque Prioritario'!$F16,"") | V15: =IF(AND('Hitos del Enfoque Prioritario'!C16='Data Validation'!$A$2,'Hitos del Enfoque Prioritario'!F16=""),"CORRECT",IF('Hitos del Enfoque Prioritario'!C16='Data Validation'!$A$3,"CORRECT",IF('Hitos del Enfoque Prioritario'!B16=1,"ERROR 1",'Data Validation'!$A$4))) -> N/A | W15: =IF(AND('Hitos del Enfoque Prioritario'!C16='Data Validation'!$A$2,'Hitos del Enfoque Prioritario'!F16=""),"CORRECT",IF('Hitos del Enfoque Prioritario'!C16='Data Validation'!$A$3,"CORRECT",IF('Hitos del Enfoque Prioritario'!B16=2,"ERROR 1",'Data Validation'!$A$4))) -> N/A | X15: =IF(AND('Hitos del Enfoque Prioritario'!C16='Data Validation'!$A$2,'Hitos del Enfoque Prioritario'!F16=""),"CORRECT",IF('Hitos del Enfoque Prioritario'!C16='Data Validation'!$A$3,"CORRECT",IF('Hitos del Enfoque Prioritario'!B16=3,"ERROR 1",'Data Validation'!$A$4))) -> N/A | Y15: =IF(AND('Hitos del Enfoque Prioritario'!C16='Data Validation'!$A$2,'Hitos del Enfoque Prioritario'!F16=""),"CORRECT",IF('Hitos del Enfoque Prioritario'!C16='Data Validation'!$A$3,"CORRECT",IF('Hitos del Enfoque Prioritario'!B16=4,"ERROR 1",'Data Validation'!$A$4))) -> N/A | Z15: =IF(AND('Hitos del Enfoque Prioritario'!C16='Data Validation'!$A$2,'Hitos del Enfoque Prioritario'!F16=""),"CORRECT",IF('Hitos del Enfoque Prioritario'!C16='Data Validation'!$A$3,"CORRECT",IF('Hitos del Enfoque Prioritario'!B16=5,"ERROR 1",'Data Validation'!$A$4))) -> N/A | AA15: =IF(AND('Hitos del Enfoque Prioritario'!C16='Data Validation'!$A$2,'Hitos del Enfoque Prioritario'!F16=""),"CORRECT",IF('Hitos del Enfoque Prioritario'!C16='Data Validation'!$A$3,"CORRECT",IF('Hitos del Enfoque Prioritario'!B16=6,"ERROR 1",'Data Validation'!$A$4))) -> N/A | AB15: =IF(AND('Hitos del Enfoque Prioritario'!C16='Data Validation'!$A$3,'Hitos del Enfoque Prioritario'!F16=""),IF('Hitos del Enfoque Prioritario'!B16=1,"ERROR 2",'Data Validation'!$A$4),"CORRECT") -> CORRECT | AC15: =IF(AND('Hitos del Enfoque Prioritario'!C16='Data Validation'!$A$3,'Hitos del Enfoque Prioritario'!F16=""),IF('Hitos del Enfoque Prioritario'!B16=2,"ERROR 2",'Data Validation'!$A$4),"CORRECT") -> CORRECT | AD15: =IF(AND('Hitos del Enfoque Prioritario'!C16='Data Validation'!$A$3,'Hitos del Enfoque Prioritario'!F16=""),IF('Hitos del Enfoque Prioritario'!B16=3,"ERROR 2",'Data Validation'!$A$4),"CORRECT") -> CORRECT | AE15: =IF(AND('Hitos del Enfoque Prioritario'!C16='Data Validation'!$A$3,'Hitos del Enfoque Prioritario'!F16=""),IF('Hitos del Enfoque Prioritario'!B16=4,"ERROR 2",'Data Validation'!$A$4),"CORRECT") -> CORRECT | AF15: =IF(AND('Hitos del Enfoque Prioritario'!C16='Data Validation'!$A$3,'Hitos del Enfoque Prioritario'!F16=""),IF('Hitos del Enfoque Prioritario'!B16=5,"ERROR 2",'Data Validation'!$A$4),"CORRECT") -> CORRECT | AG15: =IF(AND('Hitos del Enfoque Prioritario'!C16='Data Validation'!$A$3,'Hitos del Enfoque Prioritario'!F16=""),IF('Hitos del Enfoque Prioritario'!B16=6,"ERROR 2",'Data Validation'!$A$4),"CORRECT") -> CORRECT
... A340: =COUNTIFS('Hitos del Enfoque Prioritario'!B341,"1",'Hitos del Enfoque Prioritario'!C341,'Data Validation'!$A$2) -> 0 | B340: =COUNTIFS('Hitos del Enfoque Prioritario'!B341,"2",'Hitos del Enfoque Prioritario'!C341,'Data Validation'!$A$2) -> 0 | C340: =COUNTIFS('Hitos del Enfoque Prioritario'!B341,"3",'Hitos del Enfoque Prioritario'!C341,'Data Validation'!$A$2) -> 0 | D340: =COUNTIFS('Hitos del Enfoque Prioritario'!B341,"4",'Hitos del Enfoque Prioritario'!C341,'Data Validation'!$A$2) -> 0 | E340: =COUNTIFS('Hitos del Enfoque Prioritario'!B341,"5",'Hitos del Enfoque Prioritario'!C341,'Data Validation'!$A$2) -> 0 | F340: =COUNTIFS('Hitos del Enfoque Prioritario'!B341,"6",'Hitos del Enfoque Prioritario'!C341,'Data Validation'!$A$2) -> 0 | G340: =SUM(A340:F340) -> 0 | H340: =COUNTIFS('Hitos del Enfoque Prioritario'!B341,"1",'Hitos del Enfoque Prioritario'!C341,'Data Validation'!$A$4) -> 0 | I340: =COUNTIFS('Hitos del Enfoque Prioritario'!B341,"2",'Hitos del Enfoque Prioritario'!C341,'Data Validation'!$A$4) -> 0 | J340: =COUNTIFS('Hitos del Enfoque Prioritario'!B341,"3",'Hitos del Enfoque Prioritario'!C341,'Data Validation'!$A$4) -> 0 | K340: =COUNTIFS('Hitos del Enfoque Prioritario'!B341,"4",'Hitos del Enfoque Prioritario'!C341,'Data Validation'!$A$4) -> 0 | L340: =COUNTIFS('Hitos del Enfoque Prioritario'!B341,"5",'Hitos del Enfoque Prioritario'!C341,'Data Validation'!$A$4) -> 0 | M340: =COUNTIFS('Hitos del Enfoque Prioritario'!B341,"6",'Hitos del Enfoque Prioritario'!C341,'Data Validation'!$A$4) -> 0 | N340: =SUM(H340:M340) -> 0 | P340: =IF('Hitos del Enfoque Prioritario'!$B341=1,'Hitos del Enfoque Prioritario'!$F341,"") | Q340: =IF('Hitos del Enfoque Prioritario'!$B341=2,'Hitos del Enfoque Prioritario'!$F341,"") -> 0 | R340: =IF('Hitos del Enfoque Prioritario'!$B341=3,'Hitos del Enfoque Prioritario'!$F341,"") | S340: =IF('Hitos del Enfoque Prioritario'!$B341=4,'Hitos del Enfoque Prioritario'!$F341,"") | T340: =IF('Hitos del Enfoque Prioritario'!$B341=5,'Hitos del Enfoque Prioritario'!$F341,"") | U340: =IF('Hitos del Enfoque Prioritario'!$B341=6,'Hitos del Enfoque Prioritario'!$F341,"") | V340: =IF(AND('Hitos del Enfoque Prioritario'!C341='Data Validation'!$A$2,'Hitos del Enfoque Prioritario'!F341=""),"CORRECT",IF('Hitos del Enfoque Prioritario'!C341='Data Validation'!$A$3,"CORRECT",IF('Hitos del Enfoque Prioritario'!B341=1,"ERROR 1",'Data Validation'!$A$4))) -> N/A | W340: =IF(AND('Hitos del Enfoque Prioritario'!C341='Data Validation'!$A$2,'Hitos del Enfoque Prioritario'!F341=""),"CORRECT",IF('Hitos del Enfoque Prioritario'!C341='Data Validation'!$A$3,"CORRECT",IF('Hitos del Enfoque Prioritario'!B341=2,"ERROR 1",'Data Validation'!$A$4))) -> ERROR 1 | X340: =IF(AND('Hitos del Enfoque Prioritario'!C341='Data Validation'!$A$2,'Hitos del Enfoque Prioritario'!F341=""),"CORRECT",IF('Hitos del Enfoque Prioritario'!C341='Data Validation'!$A$3,"CORRECT",IF('Hitos del Enfoque Prioritario'!B341=3,"ERROR 1",'Data Validation'!$A$4))) -> N/A | Y340: =IF(AND('Hitos del Enfoque Prioritario'!C341='Data Validation'!$A$2,'Hitos del Enfoque Prioritario'!F341=""),"CORRECT",IF('Hitos del Enfoque Prioritario'!C341='Data Validation'!$A$3,"CORRECT",IF('Hitos del Enfoque Prioritario'!B341=4,"ERROR 1",'Data Validation'!$A$4))) -> N/A | Z340: =IF(AND('Hitos del Enfoque Prioritario'!C341='Data Validation'!$A$2,'Hitos del Enfoque Prioritario'!F341=""),"CORRECT",IF('Hitos del Enfoque Prioritario'!C341='Data Validation'!$A$3,"CORRECT",IF('Hitos del Enfoque Prioritario'!B341=5,"ERROR 1",'Data Validation'!$A$4))) -> N/A | AA340: =IF(AND('Hitos del Enfoque Prioritario'!C341='Data Validation'!$A$2,'Hitos del Enfoque Prioritario'!F341=""),"CORRECT",IF('Hitos del Enfoque Prioritario'!C341='Data Validation'!$A$3,"CORRECT",IF('Hitos del Enfoque Prioritario'!B341=6,"ERROR 1",'Data Validation'!$A$4))) -> N/A | AB340: =IF(AND('Hitos del Enfoque Prioritario'!C341='Data Validation'!$A$3,'Hitos del Enfoque Prioritario'!F341=""),IF('Hitos del Enfoque Prioritario'!B341=1,"ERROR 2",'Data Validation'!$A$4),"CORRECT") -> CORRECT | AC340: =IF(AND('Hitos del Enfoque Prioritario'!C341='Data Validation'!$A$3,'Hitos del Enfoque Prioritario'!F341=""),IF('Hitos del Enfoque Prioritario'!B341=2,"ERROR 2",'Data Validation'!$A$4),"CORRECT") -> CORRECT | AD340: =IF(AND('Hitos del Enfoque Prioritario'!C341='Data Validation'!$A$3,'Hitos del Enfoque Prioritario'!F341=""),IF('Hitos del Enfoque Prioritario'!B341=3,"ERROR 2",'Data Validation'!$A$4),"CORRECT") -> CORRECT | AE340: =IF(AND('Hitos del Enfoque Prioritario'!C341='Data Validation'!$A$3,'Hitos del Enfoque Prioritario'!F341=""),IF('Hitos del Enfoque Prioritario'!B341=4,"ERROR 2",'Data Validation'!$A$4),"CORRECT") -> CORRECT | AF340: =IF(AND('Hitos del Enfoque Prioritario'!C341='Data Validation'!$A$3,'Hitos del Enfoque Prioritario'!F341=""),IF('Hitos del Enfoque Prioritario'!B341=5,"ERROR 2",'Data Validation'!$A$4),"CORRECT") -> CORRECT | AG340: =IF(AND('Hitos del Enfoque Prioritario'!C341='Data Validation'!$A$3,'Hitos del Enfoque Prioritario'!F341=""),IF('Hitos del Enfoque Prioritario'!B341=6,"ERROR 2",'Data Validation'!$A$4),"CORRECT") -> CORRECT
A341: =SUM(A4:A340) -> 0 | B341: =SUM(B4:B340) -> 0 | C341: =SUM(C4:C340) -> 0 | D341: =SUM(D4:D340) -> 0 | E341: =SUM(E4:E340) -> 0 | F341: =SUM(F4:F340) -> 0 | G341: =SUM(G4:G340) -> 0 | H341: =SUM(H4:H340) -> 0 | ... N341: =SUM(N4:N340) -> 0 | AB341: =COUNTIF(AB4:AB276,"ERROR 2") -> 0 | AC341: =COUNTIF(AC4:AC276,"ERROR 2") -> 0 | AD341: =COUNTIF(AD4:AD276,"ERROR 2") -> 0 | AE341: =COUNTIF(AE4:AE276,"ERROR 2") -> 0 | AF341: =COUNTIF(AF4:AF276,"ERROR 2") -> 0 | AG341: =COUNTIF(AG4:AG276,"ERROR 2") -> 0

Sheet Data Validation
A1: Status Please enter "yes" if fully compliant with the requirement | C1: Stage of Implementation
A2: Sí | C2: Planificación
A3: No | C3: Implementación En Progreso
A4: N/A | C4: Implementado Pero No Validado

Sheet Sheet1
A4: Row Labels | B4: Count of 1 | C4: Count of 2 | D4: Count of 3 | E4: Count of 4 | F4: Count of 5 | G4: Count of 6
A5: 1 | B5: 9
A6: 2 | C6: 32
A7: 3 | D7: 28 | G7: 2
A8: 4 | E8: 48
A9: 5 | F9: 31
A10: 6 | G10: 44
A11: (blank) | B11: 1 | C11: 1 | D11: 1 | E11: 1 | F11: 1 | G11: 1
A12: Grand Total | B12: 10 | C12: 33 | D12: 29 | E12: 49 | F12: 32 | G12: 47

Sheet Sheet2

Sheet Sheet3
A1: Milestone | B1: MS 1 | C1: MS 2 | D1: MS 3 | E1: MS 4 | F1: MS 5 | G1: MS 6
A2: Completion Date | B2: ='Resumen del Enfoque Prioritario'!E52 -> 0 | C2: ='Resumen del Enfoque Prioritario'!E53 -> 0 | D2: ='Resumen del Enfoque Prioritario'!E54 -> 0 | E2: ='Resumen del Enfoque Prioritario'!E55 -> 0 | F2: ='Resumen del Enfoque Prioritario'!E56 -> 0 | G2: ='Resumen del Enfoque Prioritario'!E57 -> 0
P5: =40724+365+365 -> 41454
